[{"date":"2014-01-02","open":30.13,"high":30.13,"low":29.64,"close":29.65,"volume":4663954},{"date":"2014-01-03","open":30.02,"high":30.06,"low":29.4,"close":29.62,"volume":4209477},{"date":"2014-01-06","open":29.8,"high":29.875,"low":29.64,"close":29.75,"volume":4406021},{"date":"2014-01-07","open":29.78,"high":29.94,"low":29.65,"close":29.92,"volume":4239220},{"date":"2014-01-08","open":29.81,"high":29.845,"low":29.515,"close":29.65,"volume":4464146},{"date":"2014-01-09","open":29.7,"high":29.765,"low":29.58,"close":29.7,"volume":5216716},{"date":"2014-01-10","open":29.9,"high":30.34,"low":29.89,"close":30.29,"volume":4978715},{"date":"2014-01-13","open":30.15,"high":30.31,"low":29.98,"close":30.14,"volume":3993333},{"date":"2014-01-14","open":30.14,"high":30.25,"low":30.0,"close":30.04,"volume":3381642},{"date":"2014-01-15","open":30.01,"high":30.07,"low":29.68,"close":29.69,"volume":6258532},{"date":"2014-01-16","open":29.74,"high":29.91,"low":29.67,"close":29.86,"volume":3883115},{"date":"2014-01-17","open":29.94,"high":29.98,"low":29.59,"close":29.59,"volume":4622554},{"date":"2014-01-21","open":29.89,"high":29.9,"low":29.54,"close":29.87,"volume":3750207},{"date":"2014-01-22","open":29.91,"high":30.2,"low":29.8367,"close":30.15,"volume":4290506},{"date":"2014-01-23","open":30.12,"high":30.21,"low":29.88,"close":30.16,"volume":3415170},{"date":"2014-01-24","open":30.05,"high":30.369,"low":29.855,"close":29.87,"volume":3600159},{"date":"2014-01-27","open":29.88,"high":29.93,"low":29.71,"close":29.75,"volume":3256280},{"date":"2014-01-28","open":29.8,"high":30.095,"low":29.72,"close":30.06,"volume":4429043},{"date":"2014-01-29","open":30.05,"high":30.26,"low":29.87,"close":30.07,"volume":5098198},{"date":"2014-01-30","open":30.13,"high":30.459,"low":30.0,"close":30.39,"volume":3758631},{"date":"2014-01-31","open":30.14,"high":30.625,"low":30.07,"close":30.57,"volume":5802949},{"date":"2014-02-03","open":30.9,"high":30.92,"low":30.41,"close":30.49,"volume":5781499},{"date":"2014-02-04","open":30.58,"high":30.6,"low":30.1,"close":30.3,"volume":4714863},{"date":"2014-02-05","open":30.23,"high":30.28,"low":30.04,"close":30.11,"volume":3206449},{"date":"2014-02-06","open":30.3,"high":30.51,"low":30.14,"close":30.29,"volume":6233995},{"date":"2014-02-07","open":30.34,"high":30.42,"low":30.16,"close":30.34,"volume":5096609},{"date":"2014-02-10","open":30.32,"high":30.75,"low":30.16,"close":30.74,"volume":4019454},{"date":"2014-02-11","open":30.7,"high":31.17,"low":30.7,"close":31.08,"volume":4112251},{"date":"2014-02-12","open":30.98,"high":31.15,"low":30.85,"close":31.09,"volume":2565911},{"date":"2014-02-13","open":30.98,"high":31.42,"low":30.97,"close":31.37,"volume":3033469},{"date":"2014-02-14","open":31.29,"high":31.52,"low":31.26,"close":31.52,"volume":2922310},{"date":"2014-02-18","open":31.67,"high":31.89,"low":31.59,"close":31.78,"volume":3055769},{"date":"2014-02-19","open":31.72,"high":31.89,"low":31.52,"close":31.61,"volume":2783798},{"date":"2014-02-20","open":31.64,"high":31.92,"low":31.62,"close":31.79,"volume":3602678},{"date":"2014-02-21","open":31.87,"high":32.055,"low":31.77,"close":31.8,"volume":3096073},{"date":"2014-02-24","open":31.91,"high":32.14,"low":31.8,"close":31.81,"volume":3769520},{"date":"2014-02-25","open":31.84,"high":32.17,"low":31.77,"close":31.91,"volume":3684539},{"date":"2014-02-26","open":31.98,"high":32.19,"low":31.92,"close":32.14,"volume":4150038},{"date":"2014-02-27","open":32.15,"high":32.2,"low":31.87,"close":31.96,"volume":3871285},{"date":"2014-02-28","open":32.1,"high":32.32,"low":32.02,"close":32.29,"volume":3714688},{"date":"2014-03-03","open":32.19,"high":32.29,"low":31.83,"close":32.01,"volume":4450625},{"date":"2014-03-04","open":32.21,"high":32.39,"low":32.12,"close":32.31,"volume":4893264},{"date":"2014-03-05","open":32.31,"high":32.34,"low":31.92,"close":32.0,"volume":5041714},{"date":"2014-03-06","open":31.64,"high":31.69,"low":31.23,"close":31.37,"volume":4107706},{"date":"2014-03-07","open":31.32,"high":31.84,"low":31.19,"close":31.84,"volume":5294117},{"date":"2014-03-10","open":31.8,"high":31.9,"low":31.62,"close":31.73,"volume":4545103},{"date":"2014-03-11","open":31.76,"high":31.85,"low":31.45,"close":31.66,"volume":3275792},{"date":"2014-03-12","open":31.63,"high":32.19,"low":31.62,"close":32.19,"volume":4576013},{"date":"2014-03-13","open":32.18,"high":32.5,"low":32.07,"close":32.37,"volume":6479022},{"date":"2014-03-14","open":32.29,"high":32.905,"low":32.24,"close":32.77,"volume":5512811},{"date":"2014-03-17","open":32.81,"high":32.84,"low":32.56,"close":32.76,"volume":3326252},{"date":"2014-03-18","open":32.74,"high":32.89,"low":32.63,"close":32.8,"volume":3094261},{"date":"2014-03-19","open":32.8,"high":32.85,"low":32.05,"close":32.21,"volume":3701150},{"date":"2014-03-20","open":32.19,"high":32.22,"low":31.8,"close":32.21,"volume":4820666},{"date":"2014-03-21","open":32.39,"high":32.815,"low":32.28,"close":32.44,"volume":7408659},{"date":"2014-03-24","open":32.49,"high":32.7,"low":32.34,"close":32.37,"volume":4237718},{"date":"2014-03-25","open":32.4,"high":32.525,"low":32.1,"close":32.37,"volume":4544425},{"date":"2014-03-26","open":32.42,"high":32.68,"low":32.305,"close":32.41,"volume":4619333},{"date":"2014-03-27","open":32.36,"high":32.875,"low":32.2601,"close":32.81,"volume":7333216},{"date":"2014-03-28","open":32.75,"high":33.0,"low":32.64,"close":32.98,"volume":2992229},{"date":"2014-03-31","open":33.01,"high":33.24,"low":32.72,"close":33.14,"volume":5860835},{"date":"2014-04-01","open":33.24,"high":33.24,"low":32.71,"close":32.77,"volume":5950513},{"date":"2014-04-02","open":32.79,"high":32.79,"low":32.41,"close":32.42,"volume":5216065},{"date":"2014-04-03","open":32.5,"high":32.61,"low":32.32,"close":32.47,"volume":3422940},{"date":"2014-04-04","open":32.35,"high":33.02,"low":32.32,"close":32.71,"volume":4423955},{"date":"2014-04-07","open":32.75,"high":33.3,"low":32.67,"close":32.8,"volume":4319758},{"date":"2014-04-08","open":32.72,"high":33.3,"low":32.53,"close":33.29,"volume":5328958},{"date":"2014-04-09","open":33.31,"high":33.35,"low":32.75,"close":33.03,"volume":5414165},{"date":"2014-04-10","open":33.1,"high":33.48,"low":32.92,"close":33.02,"volume":4595779},{"date":"2014-04-11","open":33.0,"high":33.22,"low":32.58,"close":32.6,"volume":7209730},{"date":"2014-04-14","open":32.72,"high":32.89,"low":32.57,"close":32.75,"volume":5754918},{"date":"2014-04-15","open":32.84,"high":33.34,"low":32.81,"close":33.21,"volume":6118242},{"date":"2014-04-16","open":33.33,"high":33.42,"low":33.13,"close":33.42,"volume":3152153},{"date":"2014-04-17","open":33.33,"high":33.537,"low":33.04,"close":33.14,"volume":4032422},{"date":"2014-04-21","open":33.25,"high":33.33,"low":32.79,"close":32.94,"volume":6312142},{"date":"2014-04-22","open":32.9,"high":33.01,"low":32.77,"close":32.94,"volume":5623084},{"date":"2014-04-23","open":33.0,"high":33.5622,"low":32.94,"close":33.11,"volume":8970846},{"date":"2014-04-24","open":33.29,"high":33.57,"low":33.13,"close":33.39,"volume":4423339},{"date":"2014-04-25","open":33.43,"high":33.7,"low":33.38,"close":33.55,"volume":4409552},{"date":"2014-04-28","open":33.55,"high":33.86,"low":33.43,"close":33.63,"volume":5100182},{"date":"2014-04-29","open":33.62,"high":33.8,"low":33.315,"close":33.45,"volume":4397173},{"date":"2014-04-30","open":33.44,"high":33.94,"low":33.22,"close":33.34,"volume":10413385},{"date":"2014-05-01","open":33.55,"high":34.38,"low":33.3,"close":34.21,"volume":7339905},{"date":"2014-05-02","open":33.95,"high":34.43,"low":33.7,"close":33.8,"volume":6546083},{"date":"2014-05-05","open":33.81,"high":34.38,"low":33.76,"close":34.36,"volume":4760960},{"date":"2014-05-06","open":34.19,"high":34.44,"low":34.0,"close":34.2,"volume":5650102},{"date":"2014-05-07","open":34.25,"high":34.63,"low":34.11,"close":34.5,"volume":6865988},{"date":"2014-05-08","open":34.56,"high":34.56,"low":34.0,"close":34.07,"volume":3402827},{"date":"2014-05-09","open":34.15,"high":34.21,"low":33.56,"close":33.63,"volume":4107414},{"date":"2014-05-12","open":33.75,"high":33.75,"low":33.0048,"close":33.11,"volume":4021384},{"date":"2014-05-13","open":33.17,"high":33.4,"low":33.1,"close":33.39,"volume":4329014},{"date":"2014-05-14","open":33.43,"high":33.65,"low":33.26,"close":33.55,"volume":3672793},{"date":"2014-05-15","open":33.6,"high":33.8,"low":33.55,"close":33.77,"volume":4942576},{"date":"2014-05-16","open":33.81,"high":34.15,"low":33.601,"close":34.14,"volume":7162668},{"date":"2014-05-19","open":34.12,"high":34.14,"low":33.37,"close":33.58,"volume":5953649},{"date":"2014-05-20","open":33.57,"high":33.78,"low":33.205,"close":33.27,"volume":3591562},{"date":"2014-05-21","open":33.34,"high":33.39,"low":33.14,"close":33.32,"volume":3288851},{"date":"2014-05-22","open":33.42,"high":33.67,"low":33.3601,"close":33.57,"volume":4602971},{"date":"2014-05-23","open":33.53,"high":33.73,"low":33.35,"close":33.38,"volume":3982745},{"date":"2014-05-27","open":34.01,"high":34.46,"low":33.95,"close":34.34,"volume":8641036},{"date":"2014-05-28","open":34.3,"high":34.66,"low":34.11,"close":34.64,"volume":5846901},{"date":"2014-05-29","open":34.78,"high":34.87,"low":34.405,"close":34.78,"volume":4185300},{"date":"2014-05-30","open":34.76,"high":35.12,"low":34.71,"close":35.09,"volume":4455175},{"date":"2014-06-02","open":34.99,"high":35.06,"low":34.72,"close":34.78,"volume":2632788},{"date":"2014-06-03","open":34.68,"high":35.25,"low":34.64,"close":34.99,"volume":4625150},{"date":"2014-06-04","open":34.86,"high":34.965,"low":34.69,"close":34.86,"volume":2377764},{"date":"2014-06-05","open":34.86,"high":35.08,"low":34.75,"close":34.91,"volume":3959665},{"date":"2014-06-06","open":34.57,"high":34.78,"low":34.53,"close":34.66,"volume":4142028},{"date":"2014-06-09","open":34.57,"high":34.69,"low":34.1,"close":34.22,"volume":3480226},{"date":"2014-06-10","open":34.97,"high":35.1785,"low":34.67,"close":34.69,"volume":7881306},{"date":"2014-06-11","open":34.64,"high":34.66,"low":33.68,"close":33.72,"volume":9112333},{"date":"2014-06-12","open":33.79,"high":33.82,"low":33.165,"close":33.52,"volume":7015917},{"date":"2014-06-13","open":33.62,"high":34.19,"low":33.44,"close":34.03,"volume":5573399},{"date":"2014-06-16","open":33.95,"high":34.58,"low":33.92,"close":34.27,"volume":4718970},{"date":"2014-06-17","open":34.15,"high":34.31,"low":33.99,"close":34.02,"volume":3921286},{"date":"2014-06-18","open":34.03,"high":34.72,"low":34.0,"close":34.69,"volume":4767808},{"date":"2014-06-19","open":34.26,"high":35.04,"low":34.26,"close":34.78,"volume":3966997},{"date":"2014-06-20","open":34.84,"high":34.93,"low":34.58,"close":34.62,"volume":3499074},{"date":"2014-06-23","open":34.57,"high":34.71,"low":34.245,"close":34.47,"volume":3128509},{"date":"2014-06-24","open":34.4,"high":34.7,"low":34.3899,"close":34.51,"volume":3258548},{"date":"2014-06-25","open":34.45,"high":34.65,"low":34.25,"close":34.56,"volume":3545297},{"date":"2014-06-26","open":34.58,"high":34.79,"low":34.46,"close":34.76,"volume":3424634},{"date":"2014-06-27","open":34.76,"high":35.2,"low":34.6,"close":35.19,"volume":5910819},{"date":"2014-06-30","open":35.26,"high":35.56,"low":35.01,"close":35.53,"volume":4371788},{"date":"2014-07-01","open":35.52,"high":35.52,"low":35.15,"close":35.16,"volume":3515195},{"date":"2014-07-02","open":35.08,"high":35.09,"low":34.16,"close":34.33,"volume":4036038},{"date":"2014-07-03","open":34.27,"high":34.27,"low":33.85,"close":34.03,"volume":2643827},{"date":"2014-07-07","open":33.99,"high":34.26,"low":33.89,"close":34.08,"volume":2767804},{"date":"2014-07-08","open":33.97,"high":34.21,"low":33.92,"close":34.12,"volume":3555909},{"date":"2014-07-09","open":34.22,"high":34.28,"low":33.81,"close":34.0,"volume":4000338},{"date":"2014-07-10","open":34.01,"high":34.32,"low":34.0,"close":34.24,"volume":2183855},{"date":"2014-07-11","open":34.19,"high":34.31,"low":33.71,"close":33.83,"volume":3746049},{"date":"2014-07-14","open":33.9,"high":33.93,"low":33.36,"close":33.38,"volume":4006348},{"date":"2014-07-15","open":33.37,"high":33.66,"low":33.34,"close":33.53,"volume":3185517},{"date":"2014-07-16","open":33.58,"high":33.75,"low":33.4,"close":33.65,"volume":2933839},{"date":"2014-07-17","open":33.47,"high":33.92,"low":33.29,"close":33.84,"volume":3992225},{"date":"2014-07-18","open":33.47,"high":33.92,"low":33.29,"close":33.84,"volume":3992225},{"date":"2014-07-21","open":33.63,"high":33.81,"low":33.45,"close":33.77,"volume":4188575},{"date":"2014-07-22","open":33.83,"high":33.9,"low":33.6,"close":33.64,"volume":2746276},{"date":"2014-07-23","open":33.67,"high":33.77,"low":33.56,"close":33.67,"volume":2425683},{"date":"2014-07-24","open":33.68,"high":33.829,"low":33.505,"close":33.78,"volume":2255012},{"date":"2014-07-25","open":33.76,"high":33.92,"low":33.37,"close":33.43,"volume":1991176},{"date":"2014-07-28","open":33.43,"high":34.1,"low":33.39,"close":34.04,"volume":2866439},{"date":"2014-07-29","open":34.13,"high":34.13,"low":33.69,"close":33.7,"volume":2054243},{"date":"2014-07-30","open":33.75,"high":33.93,"low":33.09,"close":33.13,"volume":3400715},{"date":"2014-07-31","open":33.06,"high":33.51,"low":32.65,"close":32.99,"volume":4606066},{"date":"2014-08-01","open":32.79,"high":33.32,"low":32.72,"close":33.14,"volume":4099640},{"date":"2014-08-04","open":33.2,"high":33.25,"low":32.37,"close":33.04,"volume":6081839},{"date":"2014-08-05","open":32.88,"high":33.09,"low":32.43,"close":32.54,"volume":3742160},{"date":"2014-08-06","open":32.4,"high":32.48,"low":31.79,"close":31.94,"volume":8253502},{"date":"2014-08-07","open":32.08,"high":32.48,"low":32.08,"close":32.39,"volume":4657243},{"date":"2014-08-08","open":32.54,"high":33.03,"low":32.54,"close":33.0,"volume":9586935},{"date":"2014-08-11","open":33.14,"high":33.26,"low":32.93,"close":33.0,"volume":3247631},{"date":"2014-08-12","open":33.01,"high":33.315,"low":32.9136,"close":33.14,"volume":3468404},{"date":"2014-08-13","open":33.13,"high":33.33,"low":32.965,"close":33.3,"volume":3977355},{"date":"2014-08-14","open":33.31,"high":33.7,"low":33.31,"close":33.68,"volume":2553962},{"date":"2014-08-15","open":33.69,"high":34.05,"low":33.64,"close":33.81,"volume":4376315},{"date":"2014-08-18","open":33.85,"high":33.95,"low":33.51,"close":33.65,"volume":2731734},{"date":"2014-08-19","open":33.73,"high":34.11,"low":33.63,"close":34.09,"volume":2940545},{"date":"2014-08-20","open":34.12,"high":34.16,"low":33.855,"close":34.08,"volume":2297572},{"date":"2014-08-21","open":34.14,"high":34.46,"low":34.12,"close":34.29,"volume":2420750},{"date":"2014-08-22","open":34.31,"high":34.46,"low":33.98,"close":34.17,"volume":2032617},{"date":"2014-08-25","open":34.22,"high":34.52,"low":34.1416,"close":34.32,"volume":2213835},{"date":"2014-08-26","open":34.43,"high":34.55,"low":33.88,"close":33.93,"volume":2848935},{"date":"2014-08-27","open":33.96,"high":34.32,"low":33.96,"close":34.3,"volume":3132438},{"date":"2014-08-28","open":34.2,"high":34.52,"low":34.14,"close":34.45,"volume":1992219},{"date":"2014-08-29","open":34.41,"high":34.64,"low":34.36,"close":34.63,"volume":3737024},{"date":"2014-09-02","open":34.53,"high":34.72,"low":34.09,"close":34.27,"volume":3047718},{"date":"2014-09-03","open":34.48,"high":34.632,"low":34.375,"close":34.5,"volume":2080208},{"date":"2014-09-04","open":34.38,"high":34.54,"low":34.2,"close":34.43,"volume":3021544},{"date":"2014-09-05","open":34.48,"high":34.64,"low":34.41,"close":34.57,"volume":3983803},{"date":"2014-09-08","open":34.22,"high":34.22,"low":33.5,"close":33.7,"volume":4676247},{"date":"2014-09-09","open":33.52,"high":33.53,"low":33.2,"close":33.32,"volume":4914060},{"date":"2014-09-10","open":33.25,"high":33.3,"low":32.81,"close":32.97,"volume":5258341},{"date":"2014-09-11","open":32.91,"high":33.255,"low":32.79,"close":33.18,"volume":4664119},{"date":"2014-09-12","open":33.03,"high":33.055,"low":32.515,"close":32.63,"volume":3512933},{"date":"2014-09-15","open":32.64,"high":32.79,"low":32.54,"close":32.64,"volume":3044882},{"date":"2014-09-16","open":32.56,"high":33.51,"low":32.53,"close":33.5,"volume":5679168},{"date":"2014-09-17","open":33.58,"high":33.85,"low":33.34,"close":33.46,"volume":4436434},{"date":"2014-09-18","open":33.46,"high":33.52,"low":33.1,"close":33.28,"volume":4124118},{"date":"2014-09-19","open":33.3,"high":33.71,"low":33.23,"close":33.64,"volume":6848308},{"date":"2014-09-22","open":33.54,"high":33.545,"low":33.15,"close":33.32,"volume":2852458},{"date":"2014-09-23","open":33.3,"high":33.38,"low":33.11,"close":33.11,"volume":2890911},{"date":"2014-09-24","open":33.15,"high":33.18,"low":32.61,"close":32.78,"volume":4339766},{"date":"2014-09-25","open":32.79,"high":33.05,"low":32.75,"close":32.82,"volume":3949166},{"date":"2014-09-26","open":32.88,"high":32.91,"low":32.41,"close":32.72,"volume":2827895},{"date":"2014-09-29","open":32.6,"high":33.01,"low":32.53,"close":32.94,"volume":3131251},{"date":"2014-09-30","open":33.02,"high":33.34,"low":32.74,"close":32.84,"volume":4104485},{"date":"2014-10-01","open":32.95,"high":33.46,"low":32.905,"close":33.1,"volume":4962561},{"date":"2014-10-02","open":33.09,"high":33.35,"low":33.02,"close":33.15,"volume":3083510},{"date":"2014-10-03","open":33.26,"high":33.58,"low":32.93,"close":33.48,"volume":2498739},{"date":"2014-10-06","open":33.5,"high":33.63,"low":33.26,"close":33.47,"volume":1631442},{"date":"2014-10-07","open":33.42,"high":34.04,"low":33.36,"close":33.58,"volume":3699576},{"date":"2014-10-08","open":33.65,"high":34.3,"low":33.6,"close":34.27,"volume":3732975},{"date":"2014-10-09","open":34.23,"high":34.49,"low":33.7,"close":33.7,"volume":4823929},{"date":"2014-10-10","open":33.78,"high":34.31,"low":33.68,"close":33.78,"volume":4525667},{"date":"2014-10-13","open":33.86,"high":34.15,"low":33.64,"close":33.64,"volume":4435618},{"date":"2014-10-14","open":33.81,"high":34.18,"low":33.37,"close":33.59,"volume":9104216},{"date":"2014-10-15","open":33.51,"high":33.72,"low":32.12,"close":32.49,"volume":11683380},{"date":"2014-10-16","open":32.12,"high":33.16,"low":32.09,"close":33.05,"volume":6203860},{"date":"2014-10-17","open":33.25,"high":33.4,"low":32.85,"close":33.35,"volume":4779476},{"date":"2014-10-20","open":33.4,"high":33.95,"low":33.36,"close":33.94,"volume":3755219},{"date":"2014-10-21","open":34.01,"high":34.08,"low":33.74,"close":33.94,"volume":2934144},{"date":"2014-10-22","open":34.0,"high":34.51,"low":33.97,"close":34.36,"volume":4691019},{"date":"2014-10-23","open":34.61,"high":34.66,"low":34.26,"close":34.35,"volume":3650483},{"date":"2014-10-24","open":34.32,"high":34.6,"low":34.22,"close":34.53,"volume":2574692},{"date":"2014-10-27","open":34.62,"high":34.75,"low":34.4,"close":34.67,"volume":3109838},{"date":"2014-10-28","open":34.7,"high":34.83,"low":34.4,"close":34.83,"volume":3830823},{"date":"2014-10-29","open":34.84,"high":34.95,"low":34.17,"close":34.51,"volume":3254749},{"date":"2014-10-30","open":36.14,"high":36.3,"low":35.75,"close":35.86,"volume":5611971},{"date":"2014-10-31","open":34.97,"high":35.02,"low":34.68,"close":34.99,"volume":6488836},{"date":"2014-11-03","open":35.02,"high":35.25,"low":34.89,"close":35.14,"volume":4330297},{"date":"2014-11-04","open":35.09,"high":35.42,"low":34.78,"close":34.94,"volume":3270759},{"date":"2014-11-05","open":35.4,"high":36.42,"low":35.23,"close":36.39,"volume":11241702},{"date":"2014-11-06","open":36.33,"high":36.33,"low":35.62,"close":35.99,"volume":7681424},{"date":"2014-11-07","open":36.0,"high":36.51,"low":35.91,"close":36.51,"volume":4160527},{"date":"2014-11-10","open":36.4,"high":36.8,"low":36.36,"close":36.78,"volume":4310879},{"date":"2014-11-11","open":36.73,"high":36.81,"low":36.46,"close":36.57,"volume":3525628},{"date":"2014-11-12","open":36.14,"high":36.3,"low":35.75,"close":35.86,"volume":5611971},{"date":"2014-11-13","open":35.92,"high":36.175,"low":35.63,"close":35.71,"volume":3242153},{"date":"2014-11-14","open":35.58,"high":35.66,"low":35.37,"close":35.44,"volume":4887578},{"date":"2014-11-17","open":35.43,"high":35.72,"low":35.29,"close":35.64,"volume":4761490},{"date":"2014-11-18","open":35.72,"high":35.92,"low":35.5,"close":35.62,"volume":3325803},{"date":"2014-11-19","open":35.52,"high":35.61,"low":35.26,"close":35.39,"volume":4992997},{"date":"2014-11-20","open":35.47,"high":35.47,"low":35.11,"close":35.26,"volume":3921300},{"date":"2014-11-21","open":35.63,"high":35.63,"low":35.205,"close":35.51,"volume":4123439},{"date":"2014-11-24","open":35.6,"high":35.68,"low":35.07,"close":35.15,"volume":3401819},{"date":"2014-11-25","open":35.24,"high":35.27,"low":34.85,"close":35.2,"volume":3854039},{"date":"2014-11-26","open":35.16,"high":35.39,"low":35.13,"close":35.24,"volume":2872281},{"date":"2014-11-28","open":35.39,"high":35.7301,"low":35.27,"close":35.53,"volume":1617999},{"date":"2014-12-01","open":35.48,"high":35.75,"low":35.31,"close":35.6,"volume":3185103},{"date":"2014-12-02","open":35.54,"high":35.9,"low":35.36,"close":35.88,"volume":4084071},{"date":"2014-12-03","open":35.85,"high":35.98,"low":35.76,"close":35.9,"volume":5829208},{"date":"2014-12-04","open":35.85,"high":36.06,"low":35.53,"close":35.63,"volume":4043372},{"date":"2014-12-05","open":35.37,"high":35.69,"low":35.09,"close":35.25,"volume":4084673},{"date":"2014-12-08","open":34.93,"high":35.385,"low":34.93,"close":35.22,"volume":3640179},{"date":"2014-12-09","open":35.08,"high":35.63,"low":35.08,"close":35.44,"volume":3633344},{"date":"2014-12-10","open":35.45,"high":35.7,"low":34.95,"close":34.98,"volume":3020454},{"date":"2014-12-11","open":35.06,"high":35.62,"low":35.06,"close":35.32,"volume":3282032},{"date":"2014-12-12","open":35.21,"high":35.51,"low":34.99,"close":35.02,"volume":3295039},{"date":"2014-12-15","open":35.05,"high":35.19,"low":34.39,"close":34.42,"volume":4226955},{"date":"2014-12-16","open":34.48,"high":34.83,"low":34.11,"close":34.2,"volume":4279504},{"date":"2014-12-17","open":34.3,"high":34.96,"low":34.25,"close":34.84,"volume":3930636},{"date":"2014-12-18","open":35.07,"high":35.8701,"low":34.93,"close":35.86,"volume":5208962},{"date":"2014-12-19","open":35.81,"high":36.275,"low":35.68,"close":36.01,"volume":6722024},{"date":"2014-12-22","open":36.46,"high":36.47,"low":35.65,"close":36.02,"volume":3998593},{"date":"2014-12-23","open":36.15,"high":36.52,"low":36.07,"close":36.39,"volume":2607795},{"date":"2014-12-24","open":36.38,"high":37.17,"low":36.38,"close":36.99,"volume":2575272},{"date":"2014-12-26","open":37.0,"high":37.56,"low":37.0,"close":37.34,"volume":3879563},{"date":"2014-12-29","open":37.35,"high":38.1399,"low":37.35,"close":37.94,"volume":3835450},{"date":"2014-12-30","open":37.81,"high":37.86,"low":37.15,"close":37.22,"volume":2369473},{"date":"2014-12-31","open":37.27,"high":37.3399,"low":36.28,"close":36.33,"volume":3521842},{"date":"2015-01-02","open":36.48,"high":36.58,"low":35.9899,"close":36.36,"volume":3770594},{"date":"2015-01-05","open":36.14,"high":36.32,"low":35.27,"close":35.52,"volume":5514405},{"date":"2015-01-06","open":35.46,"high":35.92,"low":35.28,"close":35.51,"volume":5248050},{"date":"2015-01-07","open":35.58,"high":35.89,"low":35.36,"close":35.67,"volume":4038485},{"date":"2015-01-08","open":35.81,"high":35.96,"low":35.4,"close":35.53,"volume":5508290},{"date":"2015-01-09","open":35.65,"high":35.7,"low":35.3,"close":35.35,"volume":4386803},{"date":"2015-01-12","open":35.47,"high":35.51,"low":34.855,"close":35.17,"volume":5063747},{"date":"2015-01-13","open":35.42,"high":35.68,"low":34.73,"close":34.8,"volume":10441475},{"date":"2015-01-14","open":34.76,"high":35.27,"low":34.7,"close":35.22,"volume":4437385},{"date":"2015-01-15","open":35.28,"high":35.46,"low":35.1,"close":35.32,"volume":4349861},{"date":"2015-01-16","open":35.35,"high":35.35,"low":35.08,"close":35.33,"volume":5238617},{"date":"2015-01-20","open":35.5,"high":35.63,"low":35.31,"close":35.59,"volume":3891959},{"date":"2015-01-21","open":35.42,"high":36.11,"low":35.31,"close":36.02,"volume":4304777},{"date":"2015-01-22","open":36.23,"high":36.26,"low":35.365,"close":35.7,"volume":4467190},{"date":"2015-01-23","open":35.82,"high":35.99,"low":35.7,"close":35.77,"volume":2914345},{"date":"2015-01-26","open":35.64,"high":35.72,"low":35.321,"close":35.71,"volume":2630719},{"date":"2015-01-27","open":35.56,"high":35.86,"low":35.5,"close":35.7,"volume":3168440},{"date":"2015-01-28","open":35.53,"high":36.02,"low":35.43,"close":35.52,"volume":5262096},{"date":"2015-01-29","open":35.42,"high":35.97,"low":35.2,"close":35.9,"volume":4269366},{"date":"2015-01-30","open":35.77,"high":35.95,"low":35.43,"close":35.5,"volume":5586958},{"date":"2015-02-02","open":35.5,"high":35.9,"low":35.05,"close":35.9,"volume":5087251},{"date":"2015-02-03","open":35.86,"high":36.38,"low":35.65,"close":36.38,"volume":5582323},{"date":"2015-02-04","open":36.29,"high":36.38,"low":35.76,"close":35.81,"volume":4131882},{"date":"2015-02-05","open":36.14,"high":36.74,"low":35.94,"close":36.32,"volume":3684203},{"date":"2015-02-06","open":36.14,"high":36.23,"low":35.025,"close":35.22,"volume":6803650},{"date":"2015-02-09","open":35.1,"high":35.27,"low":34.52,"close":34.65,"volume":6203877},{"date":"2015-02-10","open":34.62,"high":35.33,"low":34.62,"close":35.3,"volume":4114181},{"date":"2015-02-11","open":35.06,"high":35.14,"low":34.55,"close":34.73,"volume":4276519},{"date":"2015-02-12","open":34.74,"high":34.96,"low":34.62,"close":34.85,"volume":4995779},{"date":"2015-02-13","open":34.73,"high":34.83,"low":34.27,"close":34.69,"volume":5089693},{"date":"2015-02-17","open":34.55,"high":34.82,"low":34.32,"close":34.57,"volume":5520969},{"date":"2015-02-18","open":34.53,"high":35.46,"low":34.505,"close":35.42,"volume":5093665},{"date":"2015-02-19","open":35.43,"high":35.47,"low":34.96,"close":35.16,"volume":4823295},{"date":"2015-02-20","open":35.14,"high":35.2,"low":34.49,"close":34.98,"volume":5702468},{"date":"2015-02-23","open":35.05,"high":35.17,"low":34.78,"close":35.17,"volume":3273929},{"date":"2015-02-24","open":35.11,"high":35.48,"low":35.0,"close":35.25,"volume":3927163},{"date":"2015-02-25","open":35.14,"high":35.25,"low":34.53,"close":34.62,"volume":4316218},{"date":"2015-02-26","open":34.7,"high":34.7636,"low":34.14,"close":34.28,"volume":4383894},{"date":"2015-02-27","open":34.38,"high":34.38,"low":34.02,"close":34.1,"volume":5347508},{"date":"2015-03-02","open":34.03,"high":34.09,"low":33.18,"close":33.4,"volume":6819707},{"date":"2015-03-03","open":33.34,"high":33.59,"low":33.13,"close":33.5,"volume":3845309},{"date":"2015-03-04","open":33.38,"high":33.3828,"low":32.98,"close":33.25,"volume":3994705},{"date":"2015-03-05","open":33.4,"high":33.67,"low":33.24,"close":33.41,"volume":5565438},{"date":"2015-03-06","open":32.56,"high":32.56,"low":31.6,"close":31.74,"volume":7068037},{"date":"2015-03-09","open":31.87,"high":32.03,"low":31.52,"close":31.74,"volume":5303733},{"date":"2015-03-10","open":31.64,"high":32.05,"low":31.5203,"close":31.63,"volume":4837670},{"date":"2015-03-11","open":31.74,"high":31.8,"low":31.31,"close":31.4,"volume":3259395},{"date":"2015-03-12","open":31.63,"high":32.03,"low":31.6,"close":31.91,"volume":4736114},{"date":"2015-03-13","open":31.83,"high":31.905,"low":31.52,"close":31.8,"volume":4314927},{"date":"2015-03-16","open":31.93,"high":32.49,"low":31.93,"close":32.3,"volume":3469228},{"date":"2015-03-17","open":32.16,"high":32.53,"low":32.11,"close":32.29,"volume":4188918},{"date":"2015-03-18","open":32.3,"high":34.23,"low":32.22,"close":34.05,"volume":12947149},{"date":"2015-03-19","open":33.9,"high":34.11,"low":33.54,"close":33.69,"volume":6104977},{"date":"2015-03-20","open":33.9,"high":34.47,"low":33.83,"close":34.36,"volume":10864069},{"date":"2015-03-23","open":34.36,"high":34.39,"low":33.97,"close":34.16,"volume":5230885},{"date":"2015-03-24","open":34.22,"high":34.37,"low":33.74,"close":33.81,"volume":5578635},{"date":"2015-03-25","open":33.84,"high":33.9999,"low":33.04,"close":33.11,"volume":10860356},{"date":"2015-03-26","open":33.03,"high":33.41,"low":32.93,"close":33.02,"volume":4587998},{"date":"2015-03-27","open":33.08,"high":33.43,"low":32.87,"close":33.15,"volume":3026387},{"date":"2015-03-30","open":33.26,"high":33.65,"low":32.99,"close":33.56,"volume":4132879},{"date":"2015-03-31","open":33.46,"high":33.83,"low":33.415,"close":33.66,"volume":5808133},{"date":"2015-04-01","open":33.23,"high":33.74,"low":32.84,"close":33.67,"volume":5761411},{"date":"2015-04-02","open":33.64,"high":34.03,"low":33.64,"close":33.85,"volume":3347094},{"date":"2015-04-06","open":33.95,"high":34.6,"low":33.9,"close":34.38,"volume":4392246},{"date":"2015-04-07","open":34.38,"high":34.4,"low":33.9,"close":33.94,"volume":3165200},{"date":"2015-04-08","open":34.02,"high":34.15,"low":33.725,"close":34.08,"volume":3627637},{"date":"2015-04-09","open":33.97,"high":34.02,"low":33.41,"close":33.72,"volume":4498513},{"date":"2015-04-10","open":33.76,"high":34.17,"low":33.72,"close":34.05,"volume":4049985},{"date":"2015-04-13","open":33.98,"high":34.0,"low":33.5,"close":33.53,"volume":3315916},{"date":"2015-04-14","open":33.69,"high":33.93,"low":33.56,"close":33.86,"volume":2906817},{"date":"2015-04-15","open":33.89,"high":34.19,"low":33.51,"close":33.56,"volume":4991708},{"date":"2015-04-16","open":33.55,"high":33.55,"low":33.06,"close":33.46,"volume":4558424},{"date":"2015-04-17","open":33.33,"high":33.6,"low":33.21,"close":33.29,"volume":3044837},{"date":"2015-04-20","open":33.38,"high":33.9,"low":33.38,"close":33.8,"volume":3464693},{"date":"2015-04-21","open":33.85,"high":34.1,"low":33.5162,"close":33.61,"volume":2479984},{"date":"2015-04-22","open":33.67,"high":34.0462,"low":33.5,"close":33.97,"volume":4616926},{"date":"2015-04-23","open":33.92,"high":34.495,"low":33.9,"close":34.24,"volume":4247925},{"date":"2015-04-24","open":34.23,"high":34.72,"low":34.1,"close":34.58,"volume":4283569},{"date":"2015-04-27","open":34.24,"high":34.75,"low":33.95,"close":34.02,"volume":4333602},{"date":"2015-04-28","open":33.9,"high":34.385,"low":33.81,"close":34.37,"volume":3842616},{"date":"2015-04-29","open":34.03,"high":34.49,"low":33.96,"close":34.41,"volume":3669558},{"date":"2015-04-30","open":34.36,"high":34.49,"low":33.81,"close":34.03,"volume":5945518},{"date":"2015-05-01","open":34.12,"high":34.24,"low":33.76,"close":34.19,"volume":4769492},{"date":"2015-05-04","open":34.22,"high":34.73,"low":34.14,"close":34.45,"volume":3149382},{"date":"2015-05-05","open":34.29,"high":34.38,"low":33.7,"close":33.75,"volume":3719234},{"date":"2015-05-06","open":33.7,"high":33.84,"low":32.92,"close":33.38,"volume":5847838},{"date":"2015-05-07","open":33.57,"high":33.86,"low":33.19,"close":33.4,"volume":5431194},{"date":"2015-05-08","open":33.99,"high":34.24,"low":33.68,"close":33.9,"volume":5450945},{"date":"2015-05-11","open":33.75,"high":34.225,"low":33.72,"close":33.75,"volume":4233939},{"date":"2015-05-12","open":33.58,"high":33.76,"low":33.37,"close":33.64,"volume":4049335},{"date":"2015-05-13","open":33.67,"high":33.76,"low":33.08,"close":33.29,"volume":4229336},{"date":"2015-05-14","open":33.42,"high":33.6827,"low":33.36,"close":33.58,"volume":3268525},{"date":"2015-05-15","open":33.68,"high":34.05,"low":33.62,"close":33.93,"volume":2926019},{"date":"2015-05-18","open":33.76,"high":34.33,"low":33.68,"close":34.28,"volume":3541493},{"date":"2015-05-19","open":34.11,"high":34.75,"low":33.98,"close":34.6,"volume":6574341},{"date":"2015-05-20","open":34.63,"high":35.09,"low":34.52,"close":34.85,"volume":4737496},{"date":"2015-05-21","open":34.84,"high":34.98,"low":34.46,"close":34.56,"volume":4573440},{"date":"2015-05-22","open":34.44,"high":34.61,"low":34.13,"close":34.42,"volume":3595871},{"date":"2015-05-26","open":34.4,"high":34.44,"low":34.157,"close":34.32,"volume":3781371},{"date":"2015-05-27","open":34.46,"high":34.77,"low":34.3801,"close":34.67,"volume":3804131},{"date":"2015-05-28","open":34.67,"high":34.92,"low":34.52,"close":34.8,"volume":4345327},{"date":"2015-05-29","open":34.75,"high":34.9,"low":34.58,"close":34.71,"volume":3628440},{"date":"2015-06-01","open":34.73,"high":34.965,"low":34.56,"close":34.77,"volume":5041976},{"date":"2015-06-02","open":32.35,"high":32.42,"low":31.65,"close":31.81,"volume":10570457},{"date":"2015-06-03","open":31.9,"high":31.97,"low":31.38,"close":31.46,"volume":6317424},{"date":"2015-06-04","open":31.42,"high":31.69,"low":31.37,"close":31.45,"volume":5658197},{"date":"2015-06-05","open":31.12,"high":31.16,"low":30.75,"close":30.95,"volume":6069047},{"date":"2015-06-08","open":30.52,"high":30.57,"low":30.1,"close":30.12,"volume":7184711},{"date":"2015-06-09","open":30.17,"high":30.255,"low":30.06,"close":30.1,"volume":5471988},{"date":"2015-06-10","open":30.34,"high":30.485,"low":30.14,"close":30.22,"volume":5853134},{"date":"2015-06-11","open":30.47,"high":30.6,"low":30.3,"close":30.53,"volume":5840440},{"date":"2015-06-12","open":30.4,"high":30.51,"low":30.12,"close":30.15,"volume":3058482},{"date":"2015-06-15","open":30.13,"high":30.22,"low":29.92,"close":29.92,"volume":3994562},{"date":"2015-06-16","open":29.92,"high":30.13,"low":29.75,"close":30.03,"volume":5661950},{"date":"2015-06-17","open":30.0,"high":30.43,"low":29.95,"close":30.36,"volume":4897549},{"date":"2015-06-18","open":30.37,"high":30.96,"low":30.36,"close":30.82,"volume":4600812},{"date":"2015-06-19","open":30.7,"high":30.95,"low":30.52,"close":30.53,"volume":4645903},{"date":"2015-06-22","open":30.89,"high":30.93,"low":30.54,"close":30.61,"volume":3808281},{"date":"2015-06-23","open":30.57,"high":30.64,"low":30.03,"close":30.06,"volume":3933954},{"date":"2015-06-24","open":30.06,"high":30.21,"low":29.72,"close":29.72,"volume":4777101},{"date":"2015-06-25","open":29.82,"high":29.89,"low":29.6,"close":29.64,"volume":3430983},{"date":"2015-06-26","open":29.63,"high":29.92,"low":29.51,"close":29.75,"volume":4237350},{"date":"2015-06-29","open":29.77,"high":30.09,"low":29.44,"close":29.45,"volume":5166381},{"date":"2015-06-30","open":29.58,"high":29.6,"low":29.33,"close":29.47,"volume":6454162},{"date":"2015-07-01","open":29.66,"high":29.68,"low":29.32,"close":29.55,"volume":5556204},{"date":"2015-07-02","open":29.75,"high":30.0,"low":29.605,"close":29.8,"volume":5986652},{"date":"2015-07-06","open":29.89,"high":30.08,"low":29.775,"close":30.02,"volume":7680144},{"date":"2015-07-07","open":30.13,"high":31.05,"low":30.13,"close":30.93,"volume":7925509},{"date":"2015-07-08","open":30.79,"high":30.99,"low":30.7101,"close":30.85,"volume":5764825},{"date":"2015-07-09","open":30.98,"high":31.07,"low":30.525,"close":30.64,"volume":4454061},{"date":"2015-07-10","open":30.78,"high":31.29,"low":30.64,"close":31.03,"volume":7854946},{"date":"2015-07-13","open":31.16,"high":31.2,"low":30.82,"close":30.97,"volume":3792067},{"date":"2015-07-14","open":31.07,"high":31.17,"low":30.8449,"close":30.99,"volume":3470250},{"date":"2015-07-15","open":30.99,"high":31.23,"low":30.77,"close":31.23,"volume":4693796},{"date":"2015-07-16","open":31.23,"high":31.53,"low":31.22,"close":31.42,"volume":4679787},{"date":"2015-07-17","open":31.36,"high":31.36,"low":31.09,"close":31.1,"volume":3527441},{"date":"2015-07-20","open":31.1,"high":31.12,"low":30.8,"close":31.04,"volume":3179056},{"date":"2015-07-21","open":30.9,"high":31.04,"low":30.8,"close":30.9,"volume":3326839},{"date":"2015-07-22","open":30.89,"high":31.1999,"low":30.88,"close":30.98,"volume":4076697},{"date":"2015-07-23","open":30.95,"high":30.98,"low":30.5632,"close":30.71,"volume":4534805},{"date":"2015-07-24","open":30.68,"high":30.835,"low":30.535,"close":30.7,"volume":3662499},{"date":"2015-07-27","open":30.74,"high":31.21,"low":30.73,"close":31.06,"volume":3582124},{"date":"2015-07-28","open":31.21,"high":31.34,"low":31.03,"close":31.22,"volume":3603634},{"date":"2015-07-29","open":31.15,"high":31.3,"low":31.01,"close":31.3,"volume":3278647},{"date":"2015-07-30","open":31.14,"high":31.56,"low":31.13,"close":31.51,"volume":4286970},{"date":"2015-07-31","open":31.75,"high":32.08,"low":31.74,"close":31.81,"volume":3787922},{"date":"2015-08-03","open":31.9,"high":32.1,"low":31.7,"close":31.88,"volume":4393422},{"date":"2015-08-04","open":31.77,"high":31.85,"low":31.48,"close":31.53,"volume":2881189},{"date":"2015-08-05","open":31.67,"high":31.89,"low":31.58,"close":31.73,"volume":3036947},{"date":"2015-08-06","open":31.75,"high":32.13,"low":31.45,"close":32.09,"volume":3003308},{"date":"2015-08-07","open":32.08,"high":32.5601,"low":31.8,"close":32.36,"volume":5414243},{"date":"2015-08-10","open":32.32,"high":32.67,"low":32.32,"close":32.41,"volume":3252762},{"date":"2015-08-11","open":32.57,"high":32.82,"low":32.36,"close":32.65,"volume":3975548},{"date":"2015-08-12","open":32.54,"high":33.28,"low":32.52,"close":33.25,"volume":6109166},{"date":"2015-08-13","open":33.14,"high":33.29,"low":32.785,"close":33.15,"volume":5110108},{"date":"2015-08-14","open":33.15,"high":33.4399,"low":32.93,"close":33.36,"volume":2515550},{"date":"2015-08-17","open":33.48,"high":33.68,"low":33.285,"close":33.58,"volume":3477057},{"date":"2015-08-18","open":33.51,"high":33.55,"low":33.29,"close":33.43,"volume":3044144},{"date":"2015-08-19","open":33.32,"high":33.67,"low":33.16,"close":33.52,"volume":2775721},{"date":"2015-08-20","open":33.3,"high":33.83,"low":33.2,"close":33.37,"volume":3333855},{"date":"2015-08-21","open":33.24,"high":33.47,"low":32.9,"close":32.9,"volume":4154228},{"date":"2015-08-24","open":31.89,"high":32.47,"low":31.2,"close":31.37,"volume":7913947},{"date":"2015-08-25","open":31.9,"high":31.98,"low":30.52,"close":30.54,"volume":6989176},{"date":"2015-08-26","open":30.94,"high":31.39,"low":30.505,"close":31.28,"volume":6394931},{"date":"2015-08-27","open":31.51,"high":31.76,"low":31.2551,"close":31.75,"volume":3626743},{"date":"2015-08-28","open":31.72,"high":31.74,"low":30.925,"close":31.37,"volume":4667856},{"date":"2015-08-31","open":31.26,"high":31.29,"low":30.63,"close":30.99,"volume":4992316},{"date":"2015-09-01","open":30.6,"high":30.67,"low":29.825,"close":30.0,"volume":6138878},{"date":"2015-09-02","open":30.34,"high":30.39,"low":29.87,"close":30.15,"volume":4539725},{"date":"2015-09-03","open":30.25,"high":30.48,"low":30.07,"close":30.26,"volume":3509491},{"date":"2015-09-04","open":30.0,"high":30.06,"low":29.585,"close":29.67,"volume":4138604},{"date":"2015-09-08","open":29.71,"high":29.9,"low":29.52,"close":29.88,"volume":5852718},{"date":"2015-09-09","open":30.0,"high":30.05,"low":29.35,"close":29.41,"volume":5553647},{"date":"2015-09-10","open":29.43,"high":29.82,"low":29.4,"close":29.52,"volume":4947303},{"date":"2015-09-11","open":29.39,"high":29.67,"low":29.1762,"close":29.67,"volume":3739075},{"date":"2015-09-14","open":29.71,"high":30.085,"low":29.69,"close":29.85,"volume":4727275},{"date":"2015-09-15","open":29.91,"high":30.12,"low":29.68,"close":30.08,"volume":3395384},{"date":"2015-09-16","open":30.13,"high":30.46,"low":30.1,"close":30.33,"volume":3729585},{"date":"2015-09-17","open":30.36,"high":31.135,"low":30.27,"close":30.8,"volume":4979750},{"date":"2015-09-18","open":30.66,"high":31.23,"low":30.66,"close":30.96,"volume":7143998},{"date":"2015-09-21","open":31.06,"high":31.34,"low":31.01,"close":31.33,"volume":4778136},{"date":"2015-09-22","open":31.19,"high":31.33,"low":30.79,"close":31.04,"volume":6594439},{"date":"2015-09-23","open":31.11,"high":31.19,"low":30.86,"close":31.08,"volume":3180459},{"date":"2015-09-24","open":30.96,"high":31.695,"low":30.92,"close":31.58,"volume":5739810},{"date":"2015-09-25","open":31.61,"high":32.18,"low":31.42,"close":31.97,"volume":4284134},{"date":"2015-09-28","open":32.06,"high":32.23,"low":31.81,"close":31.9,"volume":7474368},{"date":"2015-09-29","open":31.95,"high":32.305,"low":31.91,"close":32.21,"volume":6507501},{"date":"2015-09-30","open":32.35,"high":32.91,"low":32.28,"close":32.89,"volume":5785015},{"date":"2015-10-01","open":33.0,"high":33.0,"low":32.22,"close":32.6,"volume":8029022},{"date":"2015-10-02","open":32.77,"high":33.12,"low":32.53,"close":33.04,"volume":7273580},{"date":"2015-10-05","open":33.18,"high":33.54,"low":33.0,"close":33.48,"volume":5862042},{"date":"2015-10-06","open":33.47,"high":33.5,"low":32.9,"close":33.06,"volume":5045041},{"date":"2015-10-07","open":33.07,"high":33.15,"low":32.49,"close":32.63,"volume":7015366},{"date":"2015-10-08","open":32.56,"high":33.13,"low":32.43,"close":33.09,"volume":6386493},{"date":"2015-10-09","open":33.03,"high":33.16,"low":32.91,"close":33.03,"volume":5295782},{"date":"2015-10-12","open":33.03,"high":33.4901,"low":33.03,"close":33.42,"volume":4200846},{"date":"2015-10-13","open":33.35,"high":33.57,"low":33.18,"close":33.43,"volume":5841777},{"date":"2015-10-14","open":33.46,"high":33.8089,"low":33.39,"close":33.68,"volume":3915779},{"date":"2015-10-15","open":33.81,"high":34.31,"low":33.64,"close":34.19,"volume":4656045},{"date":"2015-10-16","open":34.37,"high":34.55,"low":34.18,"close":34.46,"volume":4365307},{"date":"2015-10-19","open":34.23,"high":34.46,"low":34.01,"close":34.29,"volume":4629709},{"date":"2015-10-20","open":34.17,"high":34.44,"low":34.02,"close":34.28,"volume":3590675},{"date":"2015-10-21","open":34.43,"high":34.57,"low":34.165,"close":34.25,"volume":2871342},{"date":"2015-10-22","open":34.34,"high":34.92,"low":34.29,"close":34.75,"volume":3655885},{"date":"2015-10-23","open":34.67,"high":34.69,"low":34.05,"close":34.18,"volume":3130589},{"date":"2015-10-26","open":34.24,"high":34.33,"low":33.9,"close":34.33,"volume":3262703},{"date":"2015-10-27","open":34.19,"high":34.35,"low":34.07,"close":34.3,"volume":2963675},{"date":"2015-10-28","open":34.34,"high":34.4701,"low":33.131,"close":33.42,"volume":7043480},{"date":"2015-10-29","open":33.8,"high":33.93,"low":33.0,"close":33.79,"volume":7157745},{"date":"2015-10-30","open":33.94,"high":34.48,"low":33.82,"close":34.4,"volume":5514813},{"date":"2015-11-02","open":34.33,"high":34.48,"low":33.83,"close":34.15,"volume":5790568},{"date":"2015-11-03","open":34.1,"high":34.385,"low":33.89,"close":34.35,"volume":3143034},{"date":"2015-11-04","open":34.29,"high":34.595,"low":34.27,"close":34.52,"volume":3289412},{"date":"2015-11-05","open":34.46,"high":34.6,"low":34.22,"close":34.22,"volume":2258953},{"date":"2015-11-06","open":33.61,"high":33.74,"low":32.78,"close":33.08,"volume":6791740},{"date":"2015-11-09","open":32.99,"high":33.1699,"low":32.62,"close":33.05,"volume":3387095},{"date":"2015-11-10","open":33.07,"high":33.37,"low":33.04,"close":33.28,"volume":3427661},{"date":"2015-11-11","open":33.44,"high":34.05,"low":33.38,"close":33.99,"volume":4481039},{"date":"2015-11-12","open":33.86,"high":34.29,"low":33.29,"close":33.31,"volume":7406611},{"date":"2015-11-13","open":33.37,"high":33.7,"low":32.97,"close":33.06,"volume":4640269},{"date":"2015-11-16","open":33.12,"high":34.04,"low":33.1,"close":34.03,"volume":4382948},{"date":"2015-11-17","open":33.91,"high":34.17,"low":33.25,"close":33.37,"volume":3353595},{"date":"2015-11-18","open":33.4,"high":33.71,"low":33.0,"close":33.62,"volume":3662861},{"date":"2015-11-19","open":33.74,"high":34.17,"low":33.725,"close":34.11,"volume":4281058},{"date":"2015-11-20","open":34.33,"high":34.8,"low":34.18,"close":34.5,"volume":6515061},{"date":"2015-11-23","open":34.93,"high":35.0,"low":33.85,"close":33.97,"volume":4437614},{"date":"2015-11-24","open":33.78,"high":33.975,"low":33.4801,"close":33.93,"volume":4136236},{"date":"2015-11-25","open":33.91,"high":33.93,"low":33.42,"close":33.65,"volume":3172823},{"date":"2015-11-27","open":33.65,"high":33.79,"low":33.58,"close":33.65,"volume":2026428},{"date":"2015-11-30","open":33.72,"high":34.31,"low":33.64,"close":34.04,"volume":6453142},{"date":"2015-12-01","open":34.2,"high":34.34,"low":33.82,"close":34.2,"volume":7239042},{"date":"2015-12-02","open":34.04,"high":34.15,"low":33.09,"close":33.18,"volume":5805838},{"date":"2015-12-03","open":33.02,"high":33.18,"low":32.8535,"close":33.01,"volume":5776485},{"date":"2015-12-04","open":33.14,"high":33.8,"low":33.14,"close":33.74,"volume":5229244},{"date":"2015-12-07","open":33.62,"high":33.8,"low":33.265,"close":33.57,"volume":6527120},{"date":"2015-12-08","open":33.12,"high":33.22,"low":32.948,"close":33.11,"volume":4660115},{"date":"2015-12-09","open":32.97,"high":33.68,"low":32.94,"close":33.43,"volume":4937034},{"date":"2015-12-10","open":33.36,"high":33.41,"low":32.87,"close":32.93,"volume":3079919},{"date":"2015-12-11","open":32.73,"high":33.02,"low":32.57,"close":32.71,"volume":3855330},{"date":"2015-12-14","open":32.65,"high":32.89,"low":32.36,"close":32.77,"volume":4005874},{"date":"2015-12-15","open":32.87,"high":33.35,"low":32.81,"close":33.26,"volume":3952696},{"date":"2015-12-16","open":33.39,"high":33.91,"low":33.35,"close":33.83,"volume":5380130},{"date":"2015-12-17","open":33.81,"high":34.1,"low":33.55,"close":33.92,"volume":3339317},{"date":"2015-12-18","open":33.83,"high":33.86,"low":33.24,"close":33.64,"volume":6779605},{"date":"2015-12-21","open":33.73,"high":33.84,"low":33.27,"close":33.38,"volume":3737429},{"date":"2015-12-22","open":33.48,"high":33.91,"low":33.15,"close":33.81,"volume":4702863},{"date":"2015-12-23","open":33.97,"high":34.4,"low":33.95,"close":34.24,"volume":3840121},{"date":"2015-12-24","open":34.16,"high":34.42,"low":34.1,"close":34.26,"volume":1269091},{"date":"2015-12-28","open":34.11,"high":34.3,"low":34.02,"close":34.14,"volume":2733703},{"date":"2015-12-29","open":34.34,"high":34.48,"low":34.24,"close":34.44,"volume":2857917},{"date":"2015-12-30","open":34.45,"high":34.47,"low":34.16,"close":34.34,"volume":2568092},{"date":"2015-12-31","open":34.39,"high":34.39,"low":33.75,"close":34.13,"volume":3044711},{"date":"2016-01-04","open":33.9,"high":33.93,"low":33.37,"close":33.68,"volume":5092491},{"date":"2016-01-05","open":33.69,"high":34.1,"low":33.23,"close":34.04,"volume":5068774},{"date":"2016-01-06","open":33.77,"high":34.13,"low":33.64,"close":33.93,"volume":4119091},{"date":"2016-01-07","open":33.67,"high":33.83,"low":33.42,"close":33.54,"volume":3897710},{"date":"2016-01-08","open":33.57,"high":33.82,"low":33.325,"close":33.39,"volume":5717778},{"date":"2016-01-11","open":33.59,"high":34.01,"low":33.45,"close":33.89,"volume":5937826},{"date":"2016-01-12","open":33.99,"high":33.99,"low":33.26,"close":33.55,"volume":5806414},{"date":"2016-01-13","open":33.62,"high":33.845,"low":33.4,"close":33.5,"volume":4977456},{"date":"2016-01-14","open":33.55,"high":34.41,"low":33.23,"close":34.16,"volume":6294428},{"date":"2016-01-15","open":33.61,"high":33.99,"low":32.97,"close":33.29,"volume":6194438},{"date":"2016-01-19","open":33.55,"high":33.76,"low":33.26,"close":33.63,"volume":6161454},{"date":"2016-01-20","open":33.4,"high":33.55,"low":32.18,"close":32.8,"volume":8371482},{"date":"2016-01-21","open":32.9,"high":33.31,"low":32.62,"close":33.23,"volume":5109618},{"date":"2016-01-22","open":33.46,"high":34.1,"low":33.24,"close":34.01,"volume":4789717},{"date":"2016-01-25","open":33.98,"high":34.17,"low":33.71,"close":33.76,"volume":4359619},{"date":"2016-01-26","open":33.8,"high":34.29,"low":33.66,"close":33.83,"volume":4058270},{"date":"2016-01-27","open":33.71,"high":34.11,"low":33.54,"close":33.84,"volume":3900961},{"date":"2016-01-28","open":33.84,"high":34.5525,"low":33.6,"close":34.32,"volume":3880864},{"date":"2016-01-29","open":34.69,"high":35.15,"low":34.5,"close":35.06,"volume":5248864},{"date":"2016-02-01","open":35.15,"high":36.1,"low":35.08,"close":35.92,"volume":10278161},{"date":"2016-02-02","open":35.57,"high":36.57,"low":35.52,"close":36.37,"volume":8670801},{"date":"2016-02-03","open":36.47,"high":37.05,"low":36.36,"close":36.69,"volume":7882013},{"date":"2016-02-04","open":36.37,"high":37.23,"low":35.9,"close":36.66,"volume":8225155},{"date":"2016-02-05","open":36.32,"high":36.55,"low":35.85,"close":36.16,"volume":7619454},{"date":"2016-02-08","open":35.77,"high":36.41,"low":35.62,"close":35.99,"volume":5847797},{"date":"2016-02-09","open":35.97,"high":36.55,"low":35.75,"close":36.13,"volume":5172236},{"date":"2016-02-10","open":36.02,"high":36.47,"low":35.61,"close":36.27,"volume":4498215},{"date":"2016-02-11","open":36.1,"high":36.35,"low":35.81,"close":35.9,"volume":4446691},{"date":"2016-02-12","open":35.95,"high":36.047,"low":35.53,"close":35.74,"volume":4590845},{"date":"2016-02-16","open":35.91,"high":36.25,"low":35.6,"close":36.03,"volume":4805456},{"date":"2016-02-17","open":36.1,"high":36.2,"low":35.79,"close":35.99,"volume":3542333},{"date":"2016-02-18","open":36.06,"high":36.65,"low":35.93,"close":36.52,"volume":3729218},{"date":"2016-02-19","open":36.51,"high":36.53,"low":36.06,"close":36.26,"volume":5287347},{"date":"2016-02-22","open":36.28,"high":36.35,"low":35.5,"close":36.0,"volume":6808641},{"date":"2016-02-23","open":36.0,"high":36.36,"low":35.9,"close":36.07,"volume":3031267},{"date":"2016-02-24","open":36.0,"high":36.17,"low":35.42,"close":35.93,"volume":6767877},{"date":"2016-02-25","open":36.07,"high":36.37,"low":35.755,"close":36.35,"volume":5827714},{"date":"2016-02-26","open":36.17,"high":36.3,"low":34.75,"close":34.82,"volume":9262628},{"date":"2016-02-29","open":34.82,"high":35.59,"low":34.6442,"close":34.99,"volume":6843859},{"date":"2016-03-01","open":35.22,"high":35.32,"low":34.61,"close":34.83,"volume":6173683},{"date":"2016-03-02","open":34.7,"high":34.935,"low":34.0,"close":34.92,"volume":5463672},{"date":"2016-03-03","open":35.03,"high":35.27,"low":34.57,"close":35.26,"volume":4235573},{"date":"2016-03-04","open":35.01,"high":35.91,"low":34.82,"close":35.67,"volume":4531915},{"date":"2016-03-07","open":35.67,"high":36.18,"low":35.51,"close":36.06,"volume":5442557},{"date":"2016-03-08","open":35.67,"high":36.07,"low":35.51,"close":35.96,"volume":3934050},{"date":"2016-03-09","open":36.0,"high":36.6,"low":36.0,"close":36.46,"volume":4374065},{"date":"2016-03-10","open":36.45,"high":36.59,"low":36.14,"close":36.55,"volume":4777685},{"date":"2016-03-11","open":36.58,"high":36.77,"low":36.39,"close":36.56,"volume":3440639},{"date":"2016-03-14","open":36.45,"high":36.67,"low":36.185,"close":36.36,"volume":2698762},{"date":"2016-03-15","open":36.22,"high":36.63,"low":36.19,"close":36.51,"volume":2629930},{"date":"2016-03-16","open":36.51,"high":36.98,"low":36.135,"close":36.93,"volume":3361605},{"date":"2016-03-17","open":36.9,"high":37.68,"low":36.78,"close":37.57,"volume":5114650},{"date":"2016-03-18","open":37.44,"high":37.67,"low":37.03,"close":37.06,"volume":7565899},{"date":"2016-03-21","open":37.17,"high":37.43,"low":36.8,"close":37.19,"volume":3285486},{"date":"2016-03-22","open":37.25,"high":37.36,"low":36.955,"close":37.01,"volume":4799698},{"date":"2016-03-23","open":36.97,"high":37.245,"low":36.725,"close":37.06,"volume":4762897},{"date":"2016-03-24","open":37.06,"high":37.305,"low":36.88,"close":37.19,"volume":2370875},{"date":"2016-03-28","open":37.26,"high":37.44,"low":36.955,"close":37.17,"volume":1648748},{"date":"2016-03-29","open":37.28,"high":37.61,"low":37.11,"close":37.6,"volume":3051946},{"date":"2016-03-30","open":37.73,"high":37.85,"low":37.46,"close":37.7,"volume":2158104},{"date":"2016-03-31","open":37.66,"high":38.09,"low":37.57,"close":38.07,"volume":4788893},{"date":"2016-04-01","open":38.1,"high":38.23,"low":37.63,"close":38.19,"volume":3564638},{"date":"2016-04-04","open":38.24,"high":38.3,"low":37.78,"close":38.03,"volume":2377098},{"date":"2016-04-05","open":37.92,"high":37.99,"low":37.2,"close":37.33,"volume":4191702},{"date":"2016-04-06","open":37.28,"high":37.61,"low":36.92,"close":37.56,"volume":3917557},{"date":"2016-04-07","open":37.53,"high":37.71,"low":37.245,"close":37.36,"volume":2960580},{"date":"2016-04-08","open":37.54,"high":37.73,"low":37.29,"close":37.4,"volume":2644870},{"date":"2016-04-11","open":37.34,"high":37.68,"low":37.17,"close":37.19,"volume":2136425},{"date":"2016-04-12","open":37.22,"high":37.54,"low":37.1,"close":37.46,"volume":2252846},{"date":"2016-04-13","open":37.47,"high":37.47,"low":36.85,"close":37.11,"volume":3345355},{"date":"2016-04-14","open":36.98,"high":37.25,"low":36.95,"close":37.05,"volume":1763484},{"date":"2016-04-15","open":37.08,"high":37.59,"low":36.9801,"close":37.54,"volume":3349994},{"date":"2016-04-18","open":37.64,"high":37.79,"low":37.34,"close":37.73,"volume":2540592},{"date":"2016-04-19","open":37.8,"high":37.92,"low":37.49,"close":37.8,"volume":3349009},{"date":"2016-04-20","open":37.77,"high":37.85,"low":37.01,"close":37.05,"volume":4406839},{"date":"2016-04-21","open":37.03,"high":37.05,"low":36.14,"close":36.27,"volume":6576127},{"date":"2016-04-22","open":36.27,"high":36.58,"low":36.27,"close":36.51,"volume":2863105},{"date":"2016-04-25","open":36.5,"high":36.62,"low":36.35,"close":36.55,"volume":3261198},{"date":"2016-04-26","open":36.57,"high":36.65,"low":36.28,"close":36.46,"volume":6044632},{"date":"2016-04-27","open":36.62,"high":37.15,"low":36.46,"close":36.86,"volume":5312317},{"date":"2016-04-28","open":36.57,"high":37.29,"low":36.42,"close":37.27,"volume":4012293},{"date":"2016-04-29","open":37.29,"high":37.75,"low":36.978,"close":37.64,"volume":5430959},{"date":"2016-05-02","open":37.64,"high":38.58,"low":37.64,"close":38.35,"volume":6228189},{"date":"2016-05-03","open":38.27,"high":38.46,"low":37.9,"close":38.08,"volume":4723384},{"date":"2016-05-04","open":38.01,"high":38.605,"low":37.849,"close":38.37,"volume":3740823},{"date":"2016-05-05","open":38.28,"high":38.78,"low":38.17,"close":38.32,"volume":4598224},{"date":"2016-05-06","open":38.31,"high":38.35,"low":37.87,"close":38.3,"volume":3081572},{"date":"2016-05-09","open":38.36,"high":38.58,"low":38.28,"close":38.44,"volume":3210077},{"date":"2016-05-10","open":38.66,"high":38.71,"low":38.33,"close":38.47,"volume":4009974},{"date":"2016-05-11","open":38.57,"high":38.75,"low":38.32,"close":38.71,"volume":3430346},{"date":"2016-05-12","open":38.65,"high":39.08,"low":38.51,"close":38.91,"volume":3079792},{"date":"2016-05-13","open":38.81,"high":38.99,"low":38.61,"close":38.89,"volume":4388260},{"date":"2016-05-16","open":38.75,"high":38.86,"low":38.53,"close":38.81,"volume":5012549},{"date":"2016-05-17","open":38.74,"high":38.78,"low":38.07,"close":38.3,"volume":3958370},{"date":"2016-05-18","open":38.08,"high":38.2,"low":37.21,"close":37.48,"volume":6576306},{"date":"2016-05-19","open":37.28,"high":37.93,"low":37.1,"close":37.9,"volume":3854236},{"date":"2016-05-20","open":38.04,"high":38.0842,"low":37.76,"close":37.96,"volume":3891283},{"date":"2016-05-23","open":37.98,"high":38.05,"low":37.43,"close":37.45,"volume":4228700},{"date":"2016-05-24","open":37.63,"high":38.15,"low":37.51,"close":38.06,"volume":4609152},{"date":"2016-05-25","open":37.83,"high":38.105,"low":37.66,"close":38.0,"volume":2796323},{"date":"2016-05-26","open":38.04,"high":38.58,"low":37.92,"close":38.55,"volume":3537163},{"date":"2016-05-27","open":38.61,"high":38.695,"low":38.33,"close":38.68,"volume":3183757},{"date":"2016-05-31","open":38.59,"high":38.82,"low":38.3,"close":38.54,"volume":5126951},{"date":"2016-06-01","open":38.47,"high":38.75,"low":38.4403,"close":38.64,"volume":4451200},{"date":"2016-06-02","open":38.54,"high":38.6064,"low":38.22,"close":38.57,"volume":2738578},{"date":"2016-06-03","open":38.94,"high":39.42,"low":38.89,"close":39.3,"volume":5485305},{"date":"2016-06-06","open":39.3,"high":39.52,"low":39.04,"close":39.22,"volume":4101484},{"date":"2016-06-07","open":39.2,"high":39.5,"low":39.15,"close":39.25,"volume":4206272},{"date":"2016-06-08","open":38.73,"high":38.91,"low":38.7,"close":38.87,"volume":3730066},{"date":"2016-06-09","open":38.88,"high":39.295,"low":38.87,"close":39.25,"volume":3420826},{"date":"2016-06-10","open":39.17,"high":39.44,"low":39.125,"close":39.32,"volume":4889889},{"date":"2016-06-13","open":39.28,"high":39.48,"low":38.71,"close":38.78,"volume":7121750},{"date":"2016-06-14","open":38.86,"high":39.02,"low":38.49,"close":39.0,"volume":4726880},{"date":"2016-06-15","open":39.07,"high":39.1011,"low":38.73,"close":38.83,"volume":6038864},{"date":"2016-06-16","open":38.98,"high":39.05,"low":38.61,"close":39.0,"volume":5758505},{"date":"2016-06-17","open":38.94,"high":39.165,"low":38.85,"close":39.04,"volume":10131391},{"date":"2016-06-20","open":39.16,"high":39.82,"low":39.065,"close":39.68,"volume":7514728},{"date":"2016-06-21","open":39.64,"high":39.92,"low":39.44,"close":39.67,"volume":3633134},{"date":"2016-06-22","open":39.67,"high":39.88,"low":39.28,"close":39.31,"volume":3677095},{"date":"2016-06-23","open":39.47,"high":39.51,"low":39.17,"close":39.44,"volume":5231461},{"date":"2016-06-24","open":37.82,"high":38.5,"low":36.96,"close":37.18,"volume":16873478},{"date":"2016-06-27","open":36.8,"high":37.04,"low":36.34,"close":36.57,"volume":8933482},{"date":"2016-06-28","open":36.75,"high":36.91,"low":36.33,"close":36.66,"volume":8182083},{"date":"2016-06-29","open":36.85,"high":37.07,"low":36.63,"close":37.05,"volume":5886748},{"date":"2016-06-30","open":37.17,"high":37.81,"low":37.06,"close":37.75,"volume":7844341},{"date":"2016-07-01","open":37.8,"high":37.88,"low":37.28,"close":37.6,"volume":4513318},{"date":"2016-07-05","open":37.6,"high":37.74,"low":37.47,"close":37.62,"volume":5298253},{"date":"2016-07-06","open":37.61,"high":37.69,"low":36.85,"close":37.3,"volume":6336141},{"date":"2016-07-07","open":37.33,"high":37.42,"low":36.92,"close":36.97,"volume":5092397},{"date":"2016-07-08","open":37.07,"high":37.48,"low":36.66,"close":37.46,"volume":3948337},{"date":"2016-07-11","open":37.35,"high":37.665,"low":37.16,"close":37.64,"volume":3770108},{"date":"2016-07-12","open":37.39,"high":37.665,"low":37.25,"close":37.3,"volume":4980992},{"date":"2016-07-13","open":37.49,"high":37.56,"low":37.21,"close":37.52,"volume":4166820},{"date":"2016-07-14","open":37.26,"high":37.38,"low":37.06,"close":37.09,"volume":6094312},{"date":"2016-07-15","open":37.15,"high":37.25,"low":36.96,"close":37.15,"volume":3766197},{"date":"2016-07-18","open":37.24,"high":37.435,"low":37.17,"close":37.32,"volume":3456761},{"date":"2016-07-19","open":37.32,"high":37.42,"low":37.07,"close":37.17,"volume":3619224},{"date":"2016-07-20","open":37.21,"high":37.3,"low":36.9,"close":36.95,"volume":3804404},{"date":"2016-07-21","open":36.81,"high":37.16,"low":36.69,"close":37.13,"volume":3031862},{"date":"2016-07-22","open":37.15,"high":37.74,"low":37.12,"close":37.7,"volume":4067566},{"date":"2016-07-25","open":37.65,"high":37.69,"low":37.25,"close":37.53,"volume":3406239},{"date":"2016-07-26","open":37.51,"high":37.65,"low":36.9554,"close":37.33,"volume":4495291},{"date":"2016-07-27","open":37.25,"high":37.33,"low":36.77,"close":37.02,"volume":3738592},{"date":"2016-07-28","open":36.94,"high":37.31,"low":36.88,"close":37.24,"volume":2563992},{"date":"2016-07-29","open":37.22,"high":37.73,"low":37.22,"close":37.71,"volume":3644675},{"date":"2016-08-01","open":37.66,"high":37.76,"low":37.44,"close":37.6,"volume":2768846},{"date":"2016-08-02","open":37.45,"high":37.56,"low":37.0,"close":37.16,"volume":3725651},{"date":"2016-08-03","open":37.16,"high":37.23,"low":36.89,"close":37.1,"volume":3503830},{"date":"2016-08-04","open":37.17,"high":37.26,"low":36.86,"close":36.96,"volume":3035883},{"date":"2016-08-05","open":36.8,"high":36.93,"low":36.55,"close":36.76,"volume":4534768},{"date":"2016-08-08","open":36.89,"high":37.0565,"low":36.61,"close":36.64,"volume":4379141},{"date":"2016-08-09","open":36.37,"high":36.6,"low":35.81,"close":36.25,"volume":5184436},{"date":"2016-08-10","open":36.09,"high":36.2,"low":35.78,"close":36.03,"volume":4498614},{"date":"2016-08-11","open":36.04,"high":36.41,"low":35.9,"close":36.4,"volume":4332961},{"date":"2016-08-12","open":36.56,"high":36.75,"low":36.24,"close":36.26,"volume":3372437},{"date":"2016-08-15","open":36.26,"high":36.39,"low":35.38,"close":35.42,"volume":5367252},{"date":"2016-08-16","open":35.32,"high":35.33,"low":34.94,"close":34.97,"volume":4913168},{"date":"2016-08-17","open":34.93,"high":35.47,"low":34.56,"close":35.37,"volume":6565002},{"date":"2016-08-18","open":35.27,"high":35.6,"low":35.27,"close":35.58,"volume":4370203},{"date":"2016-08-19","open":35.38,"high":35.471,"low":34.95,"close":35.15,"volume":4016688},{"date":"2016-08-22","open":35.28,"high":35.44,"low":35.07,"close":35.42,"volume":4191471},{"date":"2016-08-23","open":35.49,"high":35.755,"low":35.255,"close":35.26,"volume":3457021},{"date":"2016-08-24","open":35.27,"high":35.4,"low":34.93,"close":35.26,"volume":4336778},{"date":"2016-08-25","open":35.34,"high":35.41,"low":35.2046,"close":35.32,"volume":2701162},{"date":"2016-08-26","open":35.31,"high":35.61,"low":34.62,"close":34.66,"volume":3505303},{"date":"2016-08-29","open":34.86,"high":35.0601,"low":34.59,"close":34.98,"volume":3078991},{"date":"2016-08-30","open":34.96,"high":35.16,"low":34.42,"close":34.51,"volume":5063494},{"date":"2016-08-31","open":34.51,"high":34.79,"low":34.35,"close":34.78,"volume":6481301},{"date":"2016-09-01","open":34.75,"high":34.84,"low":34.38,"close":34.44,"volume":4781535},{"date":"2016-09-02","open":34.61,"high":35.06,"low":34.6,"close":35.03,"volume":4873018},{"date":"2016-09-06","open":35.16,"high":35.49,"low":35.11,"close":35.32,"volume":4180018},{"date":"2016-09-07","open":34.93,"high":34.95,"low":34.5499,"close":34.71,"volume":3798266},{"date":"2016-09-08","open":34.67,"high":35.0,"low":34.67,"close":34.94,"volume":4375168},{"date":"2016-09-09","open":34.71,"high":34.71,"low":33.61,"close":33.63,"volume":5697033},{"date":"2016-09-12","open":33.53,"high":34.25,"low":33.5203,"close":34.21,"volume":6921631},{"date":"2016-09-13","open":34.2,"high":34.21,"low":33.651,"close":33.75,"volume":4794404},{"date":"2016-09-14","open":33.95,"high":34.47,"low":33.88,"close":34.13,"volume":5171894},{"date":"2016-09-15","open":34.11,"high":34.74,"low":33.98,"close":34.68,"volume":4853534},{"date":"2016-09-16","open":34.6,"high":35.12,"low":34.42,"close":35.09,"volume":7192355},{"date":"2016-09-19","open":35.16,"high":35.21,"low":34.885,"close":35.11,"volume":3970204},{"date":"2016-09-20","open":35.19,"high":35.25,"low":34.75,"close":34.77,"volume":4428375},{"date":"2016-09-21","open":34.77,"high":35.49,"low":34.75,"close":35.45,"volume":4460013},{"date":"2016-09-22","open":35.62,"high":35.885,"low":35.57,"close":35.82,"volume":3435483},{"date":"2016-09-23","open":35.5,"high":35.81,"low":35.4,"close":35.7,"volume":4155500},{"date":"2016-09-26","open":35.67,"high":35.81,"low":35.48,"close":35.76,"volume":4682299},{"date":"2016-09-27","open":35.91,"high":35.94,"low":35.14,"close":35.24,"volume":4739105},{"date":"2016-09-28","open":35.38,"high":35.48,"low":34.82,"close":35.11,"volume":4123336},{"date":"2016-09-29","open":35.02,"high":35.05,"low":34.72,"close":34.82,"volume":4647401},{"date":"2016-09-30","open":34.87,"high":35.07,"low":34.4,"close":34.57,"volume":4998489},{"date":"2016-10-03","open":34.48,"high":34.57,"low":33.71,"close":33.95,"volume":5283353},{"date":"2016-10-04","open":33.95,"high":34.0,"low":32.75,"close":32.9,"volume":9571682},{"date":"2016-10-05","open":32.95,"high":33.0,"low":32.35,"close":32.65,"volume":10898333},{"date":"2016-10-06","open":32.56,"high":32.71,"low":32.385,"close":32.5,"volume":8117127},{"date":"2016-10-07","open":32.53,"high":33.24,"low":32.08,"close":32.25,"volume":8085645},{"date":"2016-10-10","open":32.32,"high":32.57,"low":32.26,"close":32.51,"volume":3945845},{"date":"2016-10-11","open":32.46,"high":32.595,"low":32.115,"close":32.19,"volume":4339836},{"date":"2016-10-12","open":32.44,"high":32.71,"low":32.35,"close":32.52,"volume":5738189},{"date":"2016-10-13","open":32.46,"high":33.4,"low":32.37,"close":33.0,"volume":12995499},{"date":"2016-10-14","open":32.96,"high":33.17,"low":32.8,"close":32.92,"volume":5691635},{"date":"2016-10-17","open":32.95,"high":33.15,"low":32.86,"close":33.06,"volume":3411441},{"date":"2016-10-18","open":33.28,"high":33.47,"low":33.02,"close":33.41,"volume":3877357},{"date":"2016-10-19","open":33.33,"high":33.53,"low":33.23,"close":33.36,"volume":3401751},{"date":"2016-10-20","open":33.42,"high":33.68,"low":33.29,"close":33.58,"volume":5049774},{"date":"2016-10-21","open":33.42,"high":33.575,"low":33.14,"close":33.32,"volume":3454896},{"date":"2016-10-24","open":33.43,"high":33.6,"low":33.23,"close":33.53,"volume":2485034},{"date":"2016-10-25","open":33.43,"high":33.74,"low":33.4,"close":33.7,"volume":2796173},{"date":"2016-10-26","open":33.62,"high":33.91,"low":33.43,"close":33.84,"volume":2950520},{"date":"2016-10-27","open":33.67,"high":33.827,"low":33.54,"close":33.68,"volume":3846972},{"date":"2016-10-28","open":33.7,"high":33.9525,"low":33.63,"close":33.81,"volume":3562326},{"date":"2016-10-31","open":33.96,"high":34.56,"low":33.85,"close":34.34,"volume":5208645},{"date":"2016-11-01","open":34.98,"high":34.98,"low":33.87,"close":34.0,"volume":6690148},{"date":"2016-11-02","open":33.93,"high":34.11,"low":33.52,"close":33.91,"volume":4624450},{"date":"2016-11-03","open":33.91,"high":34.44,"low":33.8,"close":34.1,"volume":4769091},{"date":"2016-11-04","open":34.27,"high":34.45,"low":34.005,"close":34.02,"volume":3861508},{"date":"2016-11-07","open":34.17,"high":34.55,"low":33.84,"close":34.55,"volume":4026789},{"date":"2016-11-08","open":34.61,"high":34.93,"low":34.49,"close":34.74,"volume":3378909},{"date":"2016-11-09","open":34.05,"high":34.13,"low":33.45,"close":33.58,"volume":5569588},{"date":"2016-11-10","open":33.41,"high":33.67,"low":32.46,"close":33.11,"volume":6914564},{"date":"2016-11-11","open":33.11,"high":33.56,"low":32.97,"close":33.15,"volume":4951889},{"date":"2016-11-14","open":33.0,"high":33.09,"low":32.6,"close":32.86,"volume":7600709},{"date":"2016-11-15","open":33.0,"high":33.255,"low":32.865,"close":33.24,"volume":5239104},{"date":"2016-11-16","open":33.34,"high":33.43,"low":32.67,"close":32.87,"volume":3562041},{"date":"2016-11-17","open":32.8,"high":33.07,"low":32.755,"close":32.83,"volume":2987604},{"date":"2016-11-18","open":32.89,"high":33.1,"low":32.67,"close":32.84,"volume":2901138},{"date":"2016-11-21","open":32.98,"high":33.36,"low":32.85,"close":33.34,"volume":4023942},{"date":"2016-11-22","open":33.24,"high":33.465,"low":33.07,"close":33.32,"volume":3352141},{"date":"2016-11-23","open":33.02,"high":33.24,"low":32.7,"close":32.81,"volume":3219576},{"date":"2016-11-25","open":32.89,"high":33.46,"low":32.89,"close":33.32,"volume":1783866},{"date":"2016-11-28","open":33.41,"high":34.31,"low":33.41,"close":34.15,"volume":4966645},{"date":"2016-11-29","open":34.08,"high":34.38,"low":34.03,"close":34.19,"volume":4035469},{"date":"2016-11-30","open":33.75,"high":34.12,"low":33.46,"close":33.46,"volume":6759935},{"date":"2016-12-01","open":33.28,"high":33.34,"low":32.78,"close":33.1,"volume":4619657},{"date":"2016-12-02","open":33.32,"high":33.57,"low":33.07,"close":33.34,"volume":3488736},{"date":"2016-12-05","open":33.17,"high":33.27,"low":32.87,"close":33.25,"volume":5499019},{"date":"2016-12-06","open":33.3,"high":33.37,"low":32.94,"close":33.08,"volume":4690115},{"date":"2016-12-07","open":32.8,"high":33.11,"low":32.69,"close":33.1,"volume":4298447},{"date":"2016-12-08","open":32.9,"high":33.23,"low":32.71,"close":33.11,"volume":4636791},{"date":"2016-12-09","open":33.17,"high":33.55,"low":33.13,"close":33.51,"volume":4871078},{"date":"2016-12-12","open":33.43,"high":34.06,"low":33.39,"close":33.94,"volume":3809298},{"date":"2016-12-13","open":33.98,"high":34.2475,"low":33.86,"close":34.21,"volume":3751918},{"date":"2016-12-14","open":34.41,"high":34.62,"low":33.68,"close":33.78,"volume":4936943},{"date":"2016-12-15","open":33.56,"high":34.24,"low":33.52,"close":34.15,"volume":4126308},{"date":"2016-12-16","open":34.21,"high":34.9,"low":34.07,"close":34.63,"volume":9949666},{"date":"2016-12-19","open":34.77,"high":34.84,"low":34.14,"close":34.58,"volume":3911555},{"date":"2016-12-20","open":34.57,"high":34.7,"low":34.395,"close":34.5,"volume":3195270},{"date":"2016-12-21","open":34.46,"high":34.805,"low":34.41,"close":34.43,"volume":2770055},{"date":"2016-12-22","open":34.4,"high":34.49,"low":34.19,"close":34.46,"volume":2621166},{"date":"2016-12-23","open":34.51,"high":34.51,"low":34.105,"close":34.29,"volume":1730578},{"date":"2016-12-27","open":34.29,"high":34.36,"low":34.07,"close":34.21,"volume":2290593},{"date":"2016-12-28","open":34.28,"high":34.3,"low":33.78,"close":33.86,"volume":3203190},{"date":"2016-12-29","open":33.99,"high":34.33,"low":33.88,"close":34.26,"volume":2885678},{"date":"2016-12-30","open":34.31,"high":34.3599,"low":33.95,"close":34.05,"volume":2751938},{"date":"2017-01-03","open":34.05,"high":34.21,"low":33.78,"close":34.03,"volume":3366963},{"date":"2017-01-04","open":34.05,"high":34.51,"low":34.0,"close":34.1,"volume":3187421},{"date":"2017-01-05","open":34.17,"high":34.32,"low":33.79,"close":34.3,"volume":3497125},{"date":"2017-01-06","open":34.17,"high":34.59,"low":34.08,"close":34.56,"volume":3542674},{"date":"2017-01-09","open":34.54,"high":34.67,"low":34.16,"close":34.22,"volume":5474746},{"date":"2017-01-10","open":34.15,"high":34.1999,"low":33.72,"close":33.94,"volume":3255388},{"date":"2017-01-11","open":33.96,"high":34.32,"low":33.93,"close":34.24,"volume":2423149},{"date":"2017-01-12","open":34.23,"high":34.62,"low":34.19,"close":34.5,"volume":3872535},{"date":"2017-01-13","open":34.41,"high":34.51,"low":34.18,"close":34.36,"volume":2692933},{"date":"2017-01-17","open":34.22,"high":34.7799,"low":34.22,"close":34.69,"volume":6164678},{"date":"2017-01-18","open":34.63,"high":34.74,"low":34.48,"close":34.54,"volume":2218783},{"date":"2017-01-19","open":34.31,"high":34.56,"low":34.13,"close":34.23,"volume":2360227},{"date":"2017-01-20","open":34.29,"high":34.41,"low":34.089,"close":34.4,"volume":2596527},{"date":"2017-01-23","open":34.47,"high":34.63,"low":34.28,"close":34.36,"volume":2403104},{"date":"2017-01-24","open":34.36,"high":34.67,"low":34.26,"close":34.61,"volume":2801331},{"date":"2017-01-25","open":34.49,"high":34.66,"low":34.39,"close":34.52,"volume":2582737},{"date":"2017-01-26","open":34.5,"high":34.745,"low":34.2553,"close":34.41,"volume":2140389},{"date":"2017-01-27","open":34.5,"high":34.54,"low":34.145,"close":34.27,"volume":2556072},{"date":"2017-01-30","open":34.34,"high":34.39,"low":34.08,"close":34.38,"volume":3147583},{"date":"2017-01-31","open":34.4,"high":34.92,"low":34.345,"close":34.84,"volume":5204272},{"date":"2017-02-01","open":34.66,"high":35.39,"low":34.58,"close":34.95,"volume":4932307},{"date":"2017-02-02","open":35.09,"high":35.36,"low":34.89,"close":35.28,"volume":3231888},{"date":"2017-02-03","open":35.33,"high":35.58,"low":35.3,"close":35.46,"volume":3200182},{"date":"2017-02-06","open":35.56,"high":35.63,"low":35.22,"close":35.24,"volume":4001895},{"date":"2017-02-07","open":35.34,"high":35.49,"low":35.23,"close":35.4,"volume":2205968},{"date":"2017-02-08","open":35.31,"high":35.68,"low":35.3008,"close":35.65,"volume":2601361},{"date":"2017-02-09","open":35.6,"high":35.7,"low":35.31,"close":35.42,"volume":3444333},{"date":"2017-02-10","open":35.35,"high":35.62,"low":35.34,"close":35.5,"volume":3706985},{"date":"2017-02-13","open":35.54,"high":35.73,"low":35.36,"close":35.73,"volume":2262020},{"date":"2017-02-14","open":35.63,"high":35.68,"low":35.31,"close":35.47,"volume":2664037},{"date":"2017-02-15","open":35.23,"high":35.555,"low":35.08,"close":35.48,"volume":2317208},{"date":"2017-02-16","open":35.47,"high":35.72,"low":35.35,"close":35.72,"volume":2694712},{"date":"2017-02-17","open":35.75,"high":35.79,"low":35.34,"close":35.63,"volume":3438736},{"date":"2017-02-21","open":35.61,"high":36.11,"low":35.48,"close":36.03,"volume":2632458},{"date":"2017-02-22","open":36.06,"high":36.27,"low":35.95,"close":36.2,"volume":2367832},{"date":"2017-02-23","open":36.35,"high":36.65,"low":36.23,"close":36.52,"volume":2609592},{"date":"2017-02-24","open":36.59,"high":36.83,"low":36.43,"close":36.83,"volume":3255850},{"date":"2017-02-27","open":36.83,"high":36.86,"low":36.54,"close":36.57,"volume":3024457},{"date":"2017-02-28","open":36.57,"high":37.01,"low":36.57,"close":36.88,"volume":4154334},{"date":"2017-03-01","open":36.5,"high":36.95,"low":36.33,"close":36.73,"volume":3614903},{"date":"2017-03-02","open":36.57,"high":37.03,"low":36.55,"close":36.84,"volume":2655749},{"date":"2017-03-03","open":36.86,"high":36.8685,"low":36.4,"close":36.68,"volume":3151787},{"date":"2017-03-06","open":36.66,"high":36.8,"low":36.44,"close":36.78,"volume":2999395},{"date":"2017-03-07","open":36.76,"high":36.8899,"low":36.59,"close":36.79,"volume":3334600},{"date":"2017-03-08","open":36.08,"high":36.14,"low":35.8207,"close":36.04,"volume":4177443},{"date":"2017-03-09","open":36.01,"high":36.24,"low":35.95,"close":36.03,"volume":3192904},{"date":"2017-03-10","open":36.22,"high":36.37,"low":36.064,"close":36.32,"volume":2789171},{"date":"2017-03-13","open":36.27,"high":36.46,"low":36.19,"close":36.45,"volume":3234187},{"date":"2017-03-14","open":36.38,"high":36.45,"low":36.24,"close":36.43,"volume":1976348},{"date":"2017-03-15","open":36.49,"high":37.08,"low":36.48,"close":36.9,"volume":3548362},{"date":"2017-03-16","open":36.84,"high":36.85,"low":36.59,"close":36.74,"volume":2841519},{"date":"2017-03-17","open":36.84,"high":37.195,"low":36.77,"close":36.99,"volume":5653693},{"date":"2017-03-20","open":37.02,"high":37.13,"low":36.655,"close":36.8,"volume":2548891},{"date":"2017-03-21","open":36.79,"high":37.62,"low":36.79,"close":37.47,"volume":3871361},{"date":"2017-03-22","open":37.62,"high":37.89,"low":37.475,"close":37.64,"volume":3597502},{"date":"2017-03-23","open":37.6,"high":37.95,"low":37.525,"close":37.64,"volume":2901908},{"date":"2017-03-24","open":37.63,"high":37.8263,"low":37.49,"close":37.6,"volume":2269041},{"date":"2017-03-27","open":37.79,"high":37.91,"low":37.375,"close":37.56,"volume":3220173},{"date":"2017-03-28","open":37.4,"high":37.74,"low":37.35,"close":37.7,"volume":4009712},{"date":"2017-03-29","open":37.61,"high":37.61,"low":37.15,"close":37.44,"volume":4513179},{"date":"2017-03-30","open":37.32,"high":37.37,"low":37.09,"close":37.24,"volume":2968991},{"date":"2017-03-31","open":37.29,"high":37.6,"low":37.21,"close":37.39,"volume":3518711},{"date":"2017-04-03","open":37.38,"high":37.38,"low":36.91,"close":37.11,"volume":6326907},{"date":"2017-04-04","open":37.17,"high":37.485,"low":37.085,"close":37.37,"volume":3121149},{"date":"2017-04-05","open":37.3,"high":37.56,"low":37.21,"close":37.51,"volume":3362528},{"date":"2017-04-06","open":37.48,"high":37.5,"low":37.26,"close":37.41,"volume":3097144},{"date":"2017-04-07","open":37.48,"high":37.605,"low":37.25,"close":37.27,"volume":2586916},{"date":"2017-04-10","open":37.25,"high":37.34,"low":37.01,"close":37.28,"volume":2472921},{"date":"2017-04-11","open":37.26,"high":37.45,"low":37.1,"close":37.35,"volume":2573911},{"date":"2017-04-12","open":37.35,"high":37.78,"low":37.215,"close":37.78,"volume":3258517},{"date":"2017-04-13","open":37.73,"high":37.8,"low":37.47,"close":37.58,"volume":2756867},{"date":"2017-04-17","open":37.65,"high":37.93,"low":37.63,"close":37.93,"volume":3341667},{"date":"2017-04-18","open":37.88,"high":38.29,"low":37.88,"close":38.1,"volume":4097874},{"date":"2017-04-19","open":38.0,"high":38.04,"low":37.61,"close":37.77,"volume":3175063},{"date":"2017-04-20","open":37.76,"high":37.86,"low":37.42,"close":37.8,"volume":2645458},{"date":"2017-04-21","open":37.79,"high":38.13,"low":37.75,"close":37.93,"volume":3919936},{"date":"2017-04-24","open":37.98,"high":38.07,"low":37.72,"close":38.0,"volume":3471345},{"date":"2017-04-25","open":37.93,"high":38.16,"low":37.8615,"close":38.16,"volume":2756173},{"date":"2017-04-26","open":38.04,"high":38.26,"low":37.93,"close":37.94,"volume":2802811},{"date":"2017-04-27","open":37.93,"high":38.315,"low":37.91,"close":38.08,"volume":2067797},{"date":"2017-04-28","open":38.1,"high":38.22,"low":37.99,"close":38.11,"volume":3253957},{"date":"2017-05-01","open":38.17,"high":38.18,"low":37.88,"close":37.98,"volume":3565483},{"date":"2017-05-02","open":37.99,"high":38.18,"low":37.8,"close":38.04,"volume":2835447},{"date":"2017-05-03","open":37.99,"high":38.135,"low":37.845,"close":37.98,"volume":2904044},{"date":"2017-05-04","open":37.4,"high":38.49,"low":37.4,"close":38.44,"volume":3834148},{"date":"2017-05-05","open":38.54,"high":38.79,"low":38.37,"close":38.53,"volume":3165453},{"date":"2017-05-08","open":38.58,"high":38.72,"low":38.49,"close":38.69,"volume":2690179},{"date":"2017-05-09","open":38.61,"high":38.66,"low":38.31,"close":38.37,"volume":3356059},{"date":"2017-05-10","open":38.39,"high":38.56,"low":38.355,"close":38.53,"volume":3706072},{"date":"2017-05-11","open":38.47,"high":38.58,"low":38.26,"close":38.54,"volume":2633574},{"date":"2017-05-12","open":38.56,"high":38.84,"low":38.49,"close":38.76,"volume":1884576},{"date":"2017-05-15","open":38.75,"high":38.99,"low":38.67,"close":38.83,"volume":2134065},{"date":"2017-05-16","open":38.77,"high":38.89,"low":38.48,"close":38.48,"volume":2658086},{"date":"2017-05-17","open":38.52,"high":38.91,"low":38.48,"close":38.69,"volume":3960886},{"date":"2017-05-18","open":38.76,"high":38.98,"low":38.46,"close":38.8,"volume":3289622},{"date":"2017-05-19","open":38.77,"high":38.94,"low":38.51,"close":38.82,"volume":4762561},{"date":"2017-05-22","open":38.8,"high":39.25,"low":38.8,"close":39.15,"volume":3150868},{"date":"2017-05-23","open":39.26,"high":39.57,"low":39.18,"close":39.29,"volume":2650555},{"date":"2017-05-24","open":39.35,"high":39.6453,"low":39.35,"close":39.57,"volume":2543962},{"date":"2017-05-25","open":39.55,"high":39.94,"low":39.515,"close":39.9,"volume":2125545},{"date":"2017-05-26","open":39.84,"high":40.0,"low":39.8,"close":39.86,"volume":2144829},{"date":"2017-05-30","open":39.87,"high":39.94,"low":39.785,"close":39.87,"volume":2199570},{"date":"2017-05-31","open":39.91,"high":40.1,"low":39.65,"close":39.91,"volume":5623008},{"date":"2017-06-01","open":39.72,"high":39.97,"low":39.67,"close":39.96,"volume":3754460},{"date":"2017-06-02","open":40.19,"high":40.2,"low":39.865,"close":40.06,"volume":3490666},{"date":"2017-06-05","open":40.09,"high":40.17,"low":39.915,"close":40.02,"volume":2370613},{"date":"2017-06-06","open":40.13,"high":40.2,"low":39.87,"close":39.9,"volume":3443952},{"date":"2017-06-07","open":39.61,"high":39.8,"low":39.548,"close":39.66,"volume":4640231},{"date":"2017-06-08","open":39.62,"high":39.62,"low":39.1,"close":39.41,"volume":3708194},{"date":"2017-06-09","open":39.23,"high":39.355,"low":38.95,"close":39.2,"volume":3896439},{"date":"2017-06-12","open":39.21,"high":39.38,"low":38.71,"close":38.88,"volume":4988588},{"date":"2017-06-13","open":38.93,"high":39.05,"low":38.815,"close":38.98,"volume":2878100},{"date":"2017-06-14","open":39.27,"high":39.45,"low":39.2,"close":39.29,"volume":3878660},{"date":"2017-06-15","open":39.24,"high":39.52,"low":39.12,"close":39.44,"volume":2869012},{"date":"2017-06-16","open":39.57,"high":39.7,"low":39.4,"close":39.49,"volume":6181984},{"date":"2017-06-19","open":39.55,"high":39.7,"low":39.37,"close":39.58,"volume":3057314},{"date":"2017-06-20","open":39.52,"high":39.56,"low":39.3,"close":39.34,"volume":2891765},{"date":"2017-06-21","open":39.3,"high":39.42,"low":38.85,"close":39.39,"volume":4945192},{"date":"2017-06-22","open":39.3,"high":39.38,"low":38.98,"close":39.02,"volume":2874415},{"date":"2017-06-23","open":39.0,"high":39.14,"low":38.7,"close":38.83,"volume":3576788},{"date":"2017-06-26","open":38.99,"high":39.48,"low":38.83,"close":39.29,"volume":3743338},{"date":"2017-06-27","open":39.15,"high":39.325,"low":38.91,"close":39.02,"volume":3036005},{"date":"2017-06-28","open":39.17,"high":39.41,"low":38.79,"close":38.84,"volume":3207507},{"date":"2017-06-29","open":38.66,"high":38.78,"low":38.44,"close":38.66,"volume":3726097},{"date":"2017-06-30","open":38.74,"high":38.92,"low":38.65,"close":38.66,"volume":3114184},{"date":"2017-07-03","open":38.8,"high":38.84,"low":38.24,"close":38.28,"volume":1989331},{"date":"2017-07-05","open":38.36,"high":38.37,"low":38.06,"close":38.29,"volume":3263384},{"date":"2017-07-06","open":38.18,"high":38.28,"low":37.93,"close":38.03,"volume":3622549},{"date":"2017-07-07","open":38.03,"high":38.29,"low":38.0,"close":38.07,"volume":2333574},{"date":"2017-07-10","open":38.19,"high":38.32,"low":37.91,"close":37.94,"volume":3816970},{"date":"2017-07-11","open":38.0,"high":38.06,"low":37.54,"close":37.76,"volume":3229358},{"date":"2017-07-12","open":37.98,"high":38.08,"low":37.69,"close":37.8,"volume":4301118},{"date":"2017-07-13","open":37.74,"high":37.8,"low":37.44,"close":37.44,"volume":2511211},{"date":"2017-07-14","open":37.72,"high":37.73,"low":37.1925,"close":37.36,"volume":6090474},{"date":"2017-07-17","open":37.38,"high":37.71,"low":37.32,"close":37.67,"volume":2997748},{"date":"2017-07-18","open":37.71,"high":37.85,"low":37.58,"close":37.69,"volume":2286905},{"date":"2017-07-19","open":38.5,"high":38.5,"low":38.07,"close":38.12,"volume":5476654},{"date":"2017-07-20","open":38.12,"high":38.31,"low":37.96,"close":38.24,"volume":4100001},{"date":"2017-07-21","open":38.23,"high":38.575,"low":38.13,"close":38.55,"volume":2791627},{"date":"2017-07-24","open":38.51,"high":38.7,"low":38.275,"close":38.4,"volume":3767786},{"date":"2017-07-25","open":38.43,"high":38.48,"low":37.91,"close":37.97,"volume":2248047},{"date":"2017-07-26","open":37.94,"high":38.11,"low":37.81,"close":38.09,"volume":2871558},{"date":"2017-07-27","open":38.01,"high":38.25,"low":37.88,"close":38.12,"volume":3185815},{"date":"2017-07-28","open":38.12,"high":38.2,"low":37.86,"close":38.18,"volume":2988889},{"date":"2017-07-31","open":38.2,"high":38.41,"low":38.06,"close":38.33,"volume":3397690},{"date":"2017-08-01","open":38.99,"high":39.07,"low":38.66,"close":38.79,"volume":2562044},{"date":"2017-08-02","open":38.48,"high":38.96,"low":38.35,"close":38.96,"volume":3731364},{"date":"2017-08-03","open":38.42,"high":39.18,"low":38.35,"close":39.11,"volume":3208548},{"date":"2017-08-04","open":38.99,"high":39.07,"low":38.66,"close":38.79,"volume":2562044},{"date":"2017-08-07","open":38.7,"high":38.845,"low":38.66,"close":38.83,"volume":1581123},{"date":"2017-08-08","open":38.74,"high":38.85,"low":38.69,"close":38.83,"volume":1863594},{"date":"2017-08-09","open":38.87,"high":38.9,"low":38.56,"close":38.6,"volume":3095131},{"date":"2017-08-10","open":38.61,"high":38.83,"low":38.47,"close":38.75,"volume":1877071},{"date":"2017-08-11","open":38.74,"high":38.84,"low":38.385,"close":38.49,"volume":1661690},{"date":"2017-08-14","open":38.57,"high":38.71,"low":38.46,"close":38.67,"volume":2343541},{"date":"2017-08-15","open":38.53,"high":38.94,"low":38.51,"close":38.92,"volume":1778627},{"date":"2017-08-16","open":38.89,"high":39.14,"low":38.821,"close":39.05,"volume":1868134},{"date":"2017-08-17","open":39.06,"high":39.16,"low":38.795,"close":38.82,"volume":2235067},{"date":"2017-08-18","open":38.83,"high":39.04,"low":38.66,"close":38.92,"volume":2413049},{"date":"2017-08-21","open":38.86,"high":39.01,"low":38.74,"close":38.94,"volume":1598832},{"date":"2017-08-22","open":38.89,"high":39.04,"low":38.8,"close":39.04,"volume":3073678},{"date":"2017-08-23","open":39.01,"high":39.55,"low":38.89,"close":39.52,"volume":3034304},{"date":"2017-08-24","open":39.47,"high":39.555,"low":39.335,"close":39.5,"volume":2133903},{"date":"2017-08-25","open":39.56,"high":39.81,"low":39.5,"close":39.59,"volume":1597293},{"date":"2017-08-28","open":39.61,"high":39.68,"low":39.3,"close":39.53,"volume":2119880},{"date":"2017-08-29","open":39.59,"high":39.65,"low":39.36,"close":39.38,"volume":1443889},{"date":"2017-08-30","open":39.27,"high":39.42,"low":39.11,"close":39.18,"volume":1825193},{"date":"2017-08-31","open":39.26,"high":39.32,"low":39.17,"close":39.24,"volume":2086220},{"date":"2017-09-01","open":39.32,"high":39.4,"low":38.99,"close":39.11,"volume":1797135},{"date":"2017-09-05","open":39.17,"high":39.17,"low":38.901,"close":39.17,"volume":2270253},{"date":"2017-09-06","open":39.26,"high":39.3458,"low":39.03,"close":39.12,"volume":3054555},{"date":"2017-09-07","open":38.85,"high":39.23,"low":38.65,"close":39.16,"volume":3162384},{"date":"2017-09-08","open":39.21,"high":39.66,"low":39.075,"close":39.55,"volume":3090379},{"date":"2017-09-11","open":39.53,"high":39.9,"low":39.51,"close":39.83,"volume":3140828},{"date":"2017-09-12","open":39.72,"high":39.77,"low":38.82,"close":39.07,"volume":2861489},{"date":"2017-09-13","open":39.06,"high":39.06,"low":38.8,"close":38.82,"volume":3443105},{"date":"2017-09-14","open":38.83,"high":39.19,"low":38.65,"close":39.12,"volume":3497683},{"date":"2017-09-15","open":39.02,"high":39.32,"low":38.89,"close":39.31,"volume":6445061},{"date":"2017-09-18","open":39.31,"high":39.41,"low":38.76,"close":39.11,"volume":3970683},{"date":"2017-09-19","open":39.16,"high":39.33,"low":38.9867,"close":39.22,"volume":2989411},{"date":"2017-09-20","open":39.23,"high":39.34,"low":38.73,"close":38.84,"volume":2693780},{"date":"2017-09-21","open":38.87,"high":39.07,"low":38.76,"close":38.81,"volume":1395467},{"date":"2017-09-22","open":38.9,"high":38.935,"low":38.41,"close":38.47,"volume":2237386},{"date":"2017-09-25","open":38.46,"high":38.84,"low":38.39,"close":38.64,"volume":5187453},{"date":"2017-09-26","open":38.58,"high":38.88,"low":38.52,"close":38.74,"volume":4516131},{"date":"2017-09-27","open":38.48,"high":38.55,"low":37.61,"close":38.01,"volume":3159650},{"date":"2017-09-28","open":37.91,"high":38.265,"low":37.86,"close":38.18,"volume":2346132},{"date":"2017-09-29","open":38.21,"high":38.24,"low":37.9,"close":37.95,"volume":2866815},{"date":"2017-10-02","open":38.03,"high":38.14,"low":37.625,"close":37.72,"volume":4415419},{"date":"2017-10-03","open":37.69,"high":37.71,"low":37.09,"close":37.46,"volume":3652084},{"date":"2017-10-04","open":37.5,"high":37.68,"low":37.37,"close":37.65,"volume":4033900},{"date":"2017-10-05","open":37.59,"high":37.59,"low":37.195,"close":37.3,"volume":5561779},{"date":"2017-10-06","open":37.17,"high":37.36,"low":37.09,"close":37.32,"volume":3318091},{"date":"2017-10-09","open":37.28,"high":37.59,"low":37.28,"close":37.43,"volume":2159051},{"date":"2017-10-10","open":37.55,"high":37.99,"low":37.44,"close":37.85,"volume":2782909},{"date":"2017-10-11","open":37.76,"high":38.255,"low":37.75,"close":37.92,"volume":2463087},{"date":"2017-10-12","open":37.9,"high":38.5,"low":37.82,"close":38.37,"volume":2749841},{"date":"2017-10-13","open":38.43,"high":38.55,"low":37.48,"close":37.56,"volume":4771542},{"date":"2017-10-16","open":37.56,"high":37.7,"low":37.28,"close":37.4,"volume":3628173},{"date":"2017-10-17","open":37.41,"high":37.55,"low":37.26,"close":37.48,"volume":3152531},{"date":"2017-10-18","open":37.44,"high":37.56,"low":37.33,"close":37.52,"volume":2077009},{"date":"2017-10-19","open":37.56,"high":37.89,"low":37.55,"close":37.81,"volume":2768924},{"date":"2017-10-20","open":37.76,"high":37.905,"low":37.59,"close":37.75,"volume":3928965},{"date":"2017-10-23","open":37.87,"high":38.19,"low":37.71,"close":38.13,"volume":2709429},{"date":"2017-10-24","open":37.98,"high":38.08,"low":37.73,"close":37.92,"volume":2789665},{"date":"2017-10-25","open":37.82,"high":37.89,"low":37.22,"close":37.7061,"volume":3677475},{"date":"2017-10-26","open":37.91,"high":38.17,"low":37.67,"close":37.69,"volume":3272731},{"date":"2017-10-27","open":37.62,"high":38.0,"low":37.59,"close":37.75,"volume":2093446},{"date":"2017-10-30","open":37.75,"high":37.94,"low":37.46,"close":37.49,"volume":3243942},{"date":"2017-10-31","open":37.42,"high":37.57,"low":37.26,"close":37.56,"volume":3986851},{"date":"2017-11-01","open":37.27,"high":37.35,"low":36.33,"close":36.94,"volume":4071102},{"date":"2017-11-02","open":37.02,"high":37.19,"low":36.71,"close":36.9,"volume":3872741},{"date":"2017-11-03","open":36.79,"high":37.06,"low":36.74,"close":36.74,"volume":2723153},{"date":"2017-11-06","open":36.8,"high":36.84,"low":36.45,"close":36.51,"volume":2883558},{"date":"2017-11-07","open":36.58,"high":37.27,"low":36.53,"close":37.21,"volume":2930057},{"date":"2017-11-08","open":37.11,"high":37.355,"low":36.815,"close":36.92,"volume":3770774},{"date":"2017-11-09","open":36.77,"high":36.94,"low":36.57,"close":36.76,"volume":3690312},{"date":"2017-11-10","open":36.55,"high":36.595,"low":36.18,"close":36.29,"volume":3733357},{"date":"2017-11-13","open":36.3,"high":36.73,"low":36.29,"close":36.63,"volume":4020127},{"date":"2017-11-14","open":36.52,"high":37.1,"low":36.52,"close":37.07,"volume":3840382},{"date":"2017-11-15","open":37.15,"high":37.3396,"low":36.5,"close":36.55,"volume":3007620},{"date":"2017-11-16","open":36.5,"high":36.63,"low":36.1,"close":36.22,"volume":4874611},{"date":"2017-11-17","open":36.13,"high":36.44,"low":36.06,"close":36.26,"volume":4348092},{"date":"2017-11-20","open":36.26,"high":36.36,"low":35.865,"close":35.91,"volume":3612013},{"date":"2017-11-21","open":36.0,"high":36.24,"low":35.98,"close":36.02,"volume":3038880},{"date":"2017-11-22","open":36.0,"high":36.1,"low":35.925,"close":36.06,"volume":3221025},{"date":"2017-11-24","open":36.24,"high":36.41,"low":36.2,"close":36.31,"volume":1666725},{"date":"2017-11-27","open":36.4,"high":36.82,"low":36.25,"close":36.58,"volume":4457612},{"date":"2017-11-28","open":36.69,"high":36.99,"low":36.44,"close":36.53,"volume":3829238},{"date":"2017-11-29","open":36.49,"high":36.94,"low":36.38,"close":36.61,"volume":2463214},{"date":"2017-11-30","open":36.61,"high":36.885,"low":36.52,"close":36.67,"volume":5178374},{"date":"2017-12-01","open":36.86,"high":36.99,"low":36.21,"close":36.27,"volume":3115748},{"date":"2017-12-04","open":36.36,"high":36.4,"low":35.91,"close":35.96,"volume":3802686},{"date":"2017-12-05","open":35.97,"high":35.99,"low":35.22,"close":35.29,"volume":4564399},{"date":"2017-12-06","open":35.37,"high":35.55,"low":35.21,"close":35.41,"volume":6529314},{"date":"2017-12-07","open":34.98,"high":35.03,"low":34.72,"close":35.02,"volume":5411523},{"date":"2017-12-08","open":34.94,"high":34.94,"low":34.37,"close":34.5,"volume":10278558},{"date":"2017-12-11","open":34.49,"high":34.71,"low":34.315,"close":34.62,"volume":7836849},{"date":"2017-12-12","open":34.55,"high":34.69,"low":34.02,"close":34.04,"volume":5924888},{"date":"2017-12-13","open":34.24,"high":34.24,"low":33.87,"close":33.87,"volume":5283531},{"date":"2017-12-14","open":33.69,"high":33.9,"low":33.22,"close":33.8,"volume":4260612},{"date":"2017-12-15","open":33.87,"high":33.97,"low":33.6,"close":33.97,"volume":11020507},{"date":"2017-12-18","open":34.07,"high":34.15,"low":33.88,"close":33.97,"volume":6295389},{"date":"2017-12-19","open":33.63,"high":33.7,"low":32.4,"close":32.42,"volume":7650563},{"date":"2017-12-20","open":31.87,"high":32.15,"low":31.53,"close":31.59,"volume":19819171},{"date":"2017-12-21","open":31.53,"high":31.59,"low":31.11,"close":31.19,"volume":13655391},{"date":"2017-12-22","open":31.27,"high":31.39,"low":31.1,"close":31.13,"volume":6771871},{"date":"2017-12-26","open":31.13,"high":31.2566,"low":30.75,"close":30.76,"volume":5773948},{"date":"2017-12-27","open":30.93,"high":31.025,"low":30.74,"close":30.83,"volume":3962749},{"date":"2017-12-28","open":30.9,"high":30.98,"low":30.75,"close":30.91,"volume":5862268},{"date":"2017-12-29","open":30.91,"high":31.04,"low":30.7831,"close":30.95,"volume":3418869}]